Workbook

Sheet Ideas
A1: Idea ID | B1: Idea (proposed title) | C1: Research Question | D1: Novelty | E1: Data Feasibility | F1: Implementation Difficulty | G1: Academic Importance | H1: Practical Importance | I1: Publication Potential | J1: Risk | K1: Overall Score (formula) | L1: Rank (formula) | M1: Target Journals | N1: Hypothesis | O1: Existing Literature | P1: What Is Solved | Q1: What Remains Unsolved | R1: Exact Novelty | S1: Data Required | T1: Signals Required | U1: ML Methodology | V1: Portfolio Methodology | W1: Benchmark | X1: Experiments | Y1: Evaluation Metrics | Z1: Expected Difficulties
A2: I01 | B2: Where Does Machine-Learning Alpha Come From After Trading Costs? Nonlinearity, State Dependence and Cost-Aware Learning in Signal Combination | C2: How much of the net-of-cost value of ML signal combination is due to (a) nonlinear signal interactions, (b) state-dependent signal weights, (c) a cost-aware economic training objective, and (d) forecast-uncertainty shrinkage, and do these components interact? | D2: 8 | E2: 8 | F2: 7 | G2: 9 | H2: 9 | I2: 8 | J2: 4 | K2: =ROUND(D2*Weights!$B$4+G2*Weights!$B$5+H2*Weights!$B$6+I2*Weights!$B$7+E2*Weights!$B$8+(10-F2)*Weights!$B$9+(10-J2)*Weights!$B$10,2) | L2: =RANK(K2,$K$2:$K$16) | M2: RFS (stretch); JFQA, Management Science (target); Quantitative Finance, JFM, JBF (backup) | N2: Nonlinearity mainly raises gross IC; most net value comes from the cost-aware objective; state dependence adds net value only when trading costs are internalised (interaction effect). | O2: GKX2020; ACM2023; JKMP2026; DMNU2020; SWZ2023; DMU2024; NRRZ2024; CHK2024; AHV2023; LMNS2025 | P2: ML beats linear gross (GKX2020); ML alpha fragile to restrictions/costs (ACM2023, BHHH2023); cost-aware ML weight learning improves the implementable frontier (JKMP2026); conditional multifactor weights survive costs at factor level (DMU2024). | Q2: No unified, nested attribution of net value to nonlinearity vs conditioning vs objective vs uncertainty on one signal library, one cost model and one inference framework [inference from literature search; re-check before submission]. | R2: Factorial (2x2x2x2) nested design + multiple-testing-robust attribution (SPA/MCS, DSR, PBO) + economic mechanism tests (limits to arbitrage, liquidity regimes). | S2: CRSP, Compustat (WRDS), JKP characteristics or Open Source AP signals, FF/q factors, FRED/Welch-Goyal state variables, spread estimates | T2: ~150 published characteristics in 13 themes; liquidity/cost features | U2: Ridge; LightGBM; NN ensemble; gated mixture-of-experts; Portfolio-ML-style economic loss | V2: Common TC-aware mean-variance optimiser with partial adjustment (GP2013-style) and constraints | W2: 1/N signals, IC-weighted, Lewellen FM, KNS SDF, GKX NN, JKMP Portfolio-ML, DMNU linear PPP | X2: 16 factorial cells x 3 AUM levels x robustness grid | Y2: IC/RankIC, OOS R2, gross/net Sharpe, turnover, capacity, net alpha, CE utility | Z2: Compute; honest trial counting; cost calibration; avoiding benchmark underpowering
A3: I02 | B3: Forecasting Signal Efficacy: A Meta-Model for Dynamic Alpha Allocation under Decay and Crowding | C3: Can signal-level features (recent IC, publication age, turnover, valuation spread, crowding proxies, volatility) predict each signal's next-period net contribution, and does stock-level allocation on these forecasts beat static combination net of costs? | D3: 7 | E3: 8 | F3: 6 | G3: 7 | H3: 9 | I3: 7 | J3: 6 | K3: =ROUND(D3*Weights!$B$4+G3*Weights!$B$5+H3*Weights!$B$6+I3*Weights!$B$7+E3*Weights!$B$8+(10-F3)*Weights!$B$9+(10-J3)*Weights!$B$10,2) | L3: =RANK(K3,$K$2:$K$16) | M3: RAPS, JFQA (target); JBF, JEF, IJF (backup) | N3: Signal efficacy is predictable (factor momentum, valuation spreads) but the net benefit is concentrated in low-turnover signals. | O3: NRRZ2024; HKS2020; EL2022; KNNV2024; MP2016; CV2023 | P3: Factor returns are timeable at portfolio level (NRRZ2024, HKS2020); signals decay post-publication (MP2016). | Q3: Timing information implemented at stock level with netting and costs; crowding measures inside the meta-model. | R3: Two-level model (signal-efficacy forecasts -> stock-level cost-aware portfolio) | S3: Same as I01 + short interest, 13F ownership | T3: Same library + signal-level meta-features | U3: Panel GBDT/ridge on signal-month panel; hierarchical shrinkage | V3: TC-aware optimiser | W3: Static combination; NRRZ PLS timing; factor momentum | X3: Signal-month panel forecasting; allocation backtests | Y3: Signal-level R2; portfolio net Sharpe; turnover | Z3: Few independent time-series observations per signal; overfitting timing
A4: I03 | B4: Uncertainty-Aware Alpha Combination: Forecast Confidence, Robust Optimisation and Turnover | C4: Does using stock-level forecast uncertainty (deep ensembles, bootstrap standard errors) to shrink alpha and set robust-optimisation budgets improve net performance and reduce turnover? | D4: 6 | E4: 8 | F4: 6 | G4: 6 | H4: 8 | I4: 6 | J4: 5 | K4: =ROUND(D4*Weights!$B$4+G4*Weights!$B$5+H4*Weights!$B$6+I4*Weights!$B$7+E4*Weights!$B$8+(10-F4)*Weights!$B$9+(10-J4)*Weights!$B$10,2) | L4: =RANK(K4,$K$2:$K$16) | M4: Quantitative Finance, JFEc (target); JEF, EJOR (backup) | N4: Uncertainty shrinkage lowers turnover more than it lowers gross alpha, raising net Sharpe. | O4: LMNS2025; BS2022; GI2003; LPB2017; KZ2007 | P4: Closed-form NN forecast SEs and uncertainty-averse portfolios (LMNS2025, working paper). | Q4: Interaction with trading costs and dynamic trading; comparison of uncertainty estimators in stock-level optimisation. | R4: Uncertainty -> cost-aware robust optimiser; calibration of uncertainty to realised errors | S4: As I01 | T4: As I01 | U4: Deep ensembles, MC dropout, bootstrap SEs, conformal intervals | V4: Robust MVO with ellipsoidal uncertainty + TC | W4: Point forecasts; James-Stein alpha shrinkage; LMNS2025 method | X4: Estimator x optimiser grid | Y4: Calibration, net Sharpe, turnover | Z4: Closest prior art is very recent; risk of incremental contribution
A5: I04 | B5: Differentiable Cost-Aware Portfolio Layers for High-Dimensional Equity Signal Combination | C5: Can end-to-end training through a differentiable, constrained, cost-aware QP scale to 1,000+ stocks and beat two-stage predict-then-optimise net of costs? | D5: 7 | E5: 8 | F5: 9 | G5: 6 | H5: 7 | I5: 6 | J5: 7 | K5: =ROUND(D5*Weights!$B$4+G5*Weights!$B$5+H5*Weights!$B$6+I5*Weights!$B$7+E5*Weights!$B$8+(10-F5)*Weights!$B$9+(10-J5)*Weights!$B$10,2) | L5: =RANK(K5,$K$2:$K$16) | M5: Management Science, Operations Research, INFORMS JOC (target); QF, EJOR (backup) | N5: End-to-end training helps most when constraints bind and costs are high. | O5: BK2023; CI2023; ULM2024; EG2022; AAB2019; JKMP2026 | P5: End-to-end MVO on small universes (BK2023, ULM2024); decision-focused losses (EG2022). | Q5: Large cross-sections with realistic constraints and costs; stability. | R5: Scalable implicit differentiation with factor-structured covariance and TC | S5: As I01 | T5: As I01 | U5: NN signal combiner + differentiable QP | V5: Differentiable TC-aware QP | W5: Two-stage; JKMP2026 | X5: Scalability; net performance | Y5: Net utility, runtime, stability | Z5: Compute, gradient instability, local optima
A6: I05 | B6: Regime-Gated Mixture-of-Experts for Alpha Signal Combination | C6: Do gated experts conditioned on market states (volatility, liquidity, sentiment, momentum-crash states) outperform global models net of costs? | D6: 6 | E6: 8 | F6: 7 | G6: 5 | H6: 8 | I6: 6 | J6: 7 | K6: =ROUND(D6*Weights!$B$4+G6*Weights!$B$5+H6*Weights!$B$6+I6*Weights!$B$7+E6*Weights!$B$8+(10-F6)*Weights!$B$9+(10-J6)*Weights!$B$10,2) | L6: =RANK(K6,$K$2:$K$16) | M6: QF, JBF, JEF (target) | N6: Gating helps in crash/illiquid states (momentum, short-leg anomalies) but adds turnover. | O6: CPZ2024; DM2016; SYY2012; CDS2020; SYM2025; JJNH1991 | P6: Anomalies are state-dependent (SYY2012, MPR2026); momentum crashes are predictable (DM2016). | Q6: Learned gating for many signals with costs. | R6: MoE with economically interpretable gates | S6: As I01 + state variables | T6: As I01 | U6: MoE, jump-model regimes | V6: TC-aware optimiser | W6: Global GBDT/NN with state interactions | X6: Gate variants; placebo regimes | Y6: Net Sharpe; regime-conditional IC | Z6: Few regime episodes; overfitting
A7: I06 | B7: Learning Signal Decay: Horizon-Aware Combination with Aim Portfolios | C7: Can ML estimate signal-specific alpha term structures and embed them in Garleanu-Pedersen aim portfolios to reduce costs? | D7: 5 | E7: 8 | F7: 6 | G7: 5 | H7: 8 | I7: 5 | J7: 5 | K7: =ROUND(D7*Weights!$B$4+G7*Weights!$B$5+H7*Weights!$B$6+I7*Weights!$B$7+E7*Weights!$B$8+(10-F7)*Weights!$B$9+(10-J7)*Weights!$B$10,2) | L7: =RANK(K7,$K$2:$K$16) | M7: QF, JFM | N7: Weighting by persistence cuts turnover without sacrificing gross alpha. | O7: GP2013; BHHH2023; JKMP2026 | P7: Theory (GP2013); horizon matters for ML (BHHH2023); multi-horizon forecasts inside cost-aware portfolios (JKMP2026). | Q7: Explicit learned decay per signal/stock and its interpretability [inference]. | R7: Decay-structure estimation | S7: As I01 | T7: As I01 | U7: Multi-horizon multi-task models | V7: GP aim portfolio | W7: JKMP2026 Markowitz-ML | X7: Horizon grid | Y7: Net Sharpe, turnover | Z7: Overlap with JKMP2026
A8: I07 | B8: Netting-Aware Signal Selection: Which Signals Earn Their Keep in a Combined Portfolio? | C8: What is each signal's marginal net contribution when trades from different signals cancel? | D8: 6 | E8: 9 | F8: 5 | G8: 6 | H8: 9 | I8: 6 | J8: 4 | K8: =ROUND(D8*Weights!$B$4+G8*Weights!$B$5+H8*Weights!$B$6+I8*Weights!$B$7+E8*Weights!$B$8+(10-F8)*Weights!$B$9+(10-J8)*Weights!$B$10,2) | L8: =RANK(K8,$K$2:$K$16) | M8: JFQA, FAJ, JFM | N8: High-turnover signals add value only through netting with slow signals. | O8: DMNU2020; NMV2016; CV2023 | P8: Netting increases significant characteristics (DMNU2020, linear). | Q8: Nonlinear marginal contributions; attribution method. | R8: Shapley-style net-of-cost marginal contribution | S8: As I01 | T8: As I01 | U8: Linear + GBDT | V8: TC-aware optimiser | W8: Stand-alone signal net returns | X8: Leave-one-theme-out | Y8: Marginal net utility | Z8: Combinatorics
A9: I08 | B9: Crowding-Aware Alpha Combination | C9: Do crowding proxies (short interest, institutional ownership changes, valuation spreads) predict signal crashes and improve combination? | D9: 6 | E9: 6 | F9: 6 | G9: 5 | H9: 8 | I9: 5 | J9: 7 | K9: =ROUND(D9*Weights!$B$4+G9*Weights!$B$5+H9*Weights!$B$6+I9*Weights!$B$7+E9*Weights!$B$8+(10-F9)*Weights!$B$9+(10-J9)*Weights!$B$10,2) | L9: =RANK(K9,$K$2:$K$16) | M9: JFM, JBF | N9: Crowded signals should be down-weighted before crashes. | O9: MP2016; EL2022; LS2008 | P9: Partial evidence on crowding and factor crashes. | Q9: Stock-level implementation with costs; clean crowding measures. | R9: Crowding meta-features | S9: As I01 + 13F, short interest (Compustat) | T9: As I01 | U9: Meta-model | V9: TC-aware | W9: Static | X9: Crash prediction | Y9: Tail risk, net Sharpe | Z9: Crowding measurement noise; data access
A10: I09 | B10: Transfer Learning of Alpha Combination Across 90+ Markets | C10: Do combination functions learned in the US transfer to other markets, and does domain adaptation help net of local costs? | D10: 6 | E10: 6 | F10: 7 | G10: 6 | H10: 7 | I10: 6 | J10: 6 | K10: =ROUND(D10*Weights!$B$4+G10*Weights!$B$5+H10*Weights!$B$6+I10*Weights!$B$7+E10*Weights!$B$8+(10-F10)*Weights!$B$9+(10-J10)*Weights!$B$10,2) | L10: =RANK(K10,$K$2:$K$16) | M10: JFQA, RF, JBF | N10: Nonlinear structure transfers partially; cost structures differ. | O10: JKP2023; TH2021; CFMZ2023 | P10: Anomalies replicate globally; ML predictability global. | Q10: Transfer of combination functions with local costs. | R10: Domain adaptation | S10: JKP global + Datastream/Compustat Global | T10: JKP 153 | U10: Pretrain-finetune | V10: TC-aware | W10: Local models | X10: Country panels | Y10: Net Sharpe by market | Z10: International cost data
A11: I10 | B11: Do Text and LLM Signals Add Net-of-Cost Value to a Mature Signal Library? | C11: What is the incremental net value of news/LLM signals after controlling for 150 characteristics and costs? | D11: 7 | E11: 4 | F11: 7 | G11: 6 | H11: 8 | I11: 6 | J11: 7 | K11: =ROUND(D11*Weights!$B$4+G11*Weights!$B$5+H11*Weights!$B$6+I11*Weights!$B$7+E11*Weights!$B$8+(10-F11)*Weights!$B$9+(10-J11)*Weights!$B$10,2) | L11: =RANK(K11,$K$2:$K$16) | M11: JFQA, MS | N11: Fast text signals add gross IC but little net value except through netting. | O11: LLT2023; OP2022; CV2023 | P11: LLM scores predict short-term returns. | Q11: Incremental net value in combination. | R11: Incremental-value test with costs | S11: RavenPack/news (costly) or EDGAR text | T11: Library + text | U11: LLM embeddings + GBDT | V11: TC-aware | W11: Library-only | X11: Incremental tests | Y11: Net Sharpe, spanning | Z11: Data cost; look-ahead in LLM training
A12: I11 | B12: Graph Neural Signal Propagation with Trading Costs | C12: Do supply-chain/peer graphs improve combination net of costs? | D12: 6 | E12: 4 | F12: 8 | G12: 5 | H12: 6 | I12: 5 | J12: 7 | K12: =ROUND(D12*Weights!$B$4+G12*Weights!$B$5+H12*Weights!$B$6+I12*Weights!$B$7+E12*Weights!$B$8+(10-F12)*Weights!$B$9+(10-J12)*Weights!$B$10,2) | L12: =RANK(K12,$K$2:$K$16) | M12: QF, EJOR | N12: Graph signals are slow-moving and cheap to trade. | O12: CF2008 | P12: Customer-supplier momentum exists. | Q12: GNN combination net of costs. | R12: GNN in cost-aware setting | S12: Compustat segments / FactSet Revere (costly) | T12: Library + graph | U12: GNN | V12: TC-aware | W12: Non-graph | X12: Graph ablations | Y12: Net Sharpe | Z12: Graph data PIT
A13: I12 | B13: Bayesian Dynamic Model Averaging of Alpha Signals | C13: Does time-varying Bayesian combination beat static and ML combinations? | D13: 4 | E13: 9 | F13: 4 | G13: 4 | H13: 7 | I13: 5 | J13: 4 | K13: =ROUND(D13*Weights!$B$4+G13*Weights!$B$5+H13*Weights!$B$6+I13*Weights!$B$7+E13*Weights!$B$8+(10-F13)*Weights!$B$9+(10-J13)*Weights!$B$10,2) | L13: =RANK(K13,$K$2:$K$16) | M13: IJF, JEF | N13: Simple adaptive shrinkage matches ML net of costs. | O13: RSZ2010; KNS2020 | P13: Combination beats selection in time series. | Q13: Cross-sectional dynamic averaging net of costs. | R13: DMA for signals | S13: As I01 | T13: As I01 | U13: DMA / discounted least squares | V13: TC-aware | W13: ML | X13: Forgetting factors | Y13: Net Sharpe | Z13: Limited novelty
... A16: I15 | B16: Alpha-Risk Model Misalignment in ML Portfolios | C16: Does nonlinear ML alpha create systematic misalignment with factor risk models, and does an alignment correction improve realised risk and net returns? | D16: 6 | E16: 8 | F16: 5 | G16: 5 | H16: 8 | I16: 5 | J16: 5 | K16: =ROUND(D16*Weights!$B$4+G16*Weights!$B$5+H16*Weights!$B$6+I16*Weights!$B$7+E16*Weights!$B$8+(10-F16)*Weights!$B$9+(10-J16)*Weights!$B$10,2) | L16: =RANK(K16,$K$2:$K$16) | M16: QF, JPM, FAJ | N16: ML alpha loads on unmodelled nonlinear factors, causing risk underestimation. | O16: CSS2012; LS2008; KPS2019 | P16: Alignment problem documented for linear alphas. | Q16: Alignment for nonlinear ML alphas; learned alignment factors. | R16: Alignment diagnostics for ML | S16: As I01 | T16: As I01 | U16: GBDT/NN | V16: MVO with alpha alignment factor | W16: Standard risk model | X16: Ex-ante vs ex-post risk | Y16: Risk bias statistic, net IR | Z16: Commercial risk models unavailable; build own

Sheet Weights
A1: Scoring weights (editable - Ideas sheet recalculates)
A2: Weights should sum to 1.00
A3: Criterion | B3: Weight
A4: Novelty | B4: 0.2
A5: Academic importance | B5: 0.15
A6: Practical importance | B6: 0.1
A7: Publication potential | B7: 0.2
A8: Data feasibility | B8: 0.15
A9: Implementation ease (10 - difficulty) | B9: 0.1
A10: Safety (10 - failure risk) | B10: 0.1
A11: Sum of weights | B11: =SUM(B4:B10)

Sheet Concept_Selection
A1: Criterion | B1: A | C1: B | D1: C | E1: D | F1: E
A2: Novelty | B2: 8 | C2: 7 | D2: 6 | E2: 7 | F2: 6
A3: Academic contribution | B3: 9 | C3: 7 | D3: 6 | E3: 6 | F3: 5
A4: Practical significance | B4: 9 | C4: 9 | D4: 8 | E4: 7 | F4: 8
A5: Data feasibility | B5: 8 | C5: 8 | D5: 8 | E5: 8 | F5: 8
A6: Implementation feasibility | B6: 6 | C6: 7 | D6: 7 | E6: 4 | F6: 6
A7: Statistical rigor achievable | B7: 9 | C7: 7 | D7: 8 | E7: 7 | F7: 6
A8: Reproducibility | B8: 9 | C8: 9 | D8: 9 | E8: 7 | F8: 8
A9: Potential performance (not required to "win") | B9: 7 | C9: 7 | D9: 6 | E9: 6 | F9: 6
A10: Causal/mechanistic insight | B10: 8 | C10: 6 | D10: 6 | E10: 4 | F10: 6
A11: Journal fit (finance) | B11: 9 | C11: 8 | D11: 7 | E11: 6 | F11: 6
A12: Mean (formula) | B12: =ROUND(AVERAGE(B2:B11),2) | C12: =ROUND(AVERAGE(C2:C11),2) | D12: =ROUND(AVERAGE(D2:D11),2) | E12: =ROUND(AVERAGE(E2:E11),2) | F12: =ROUND(AVERAGE(F2:F11),2)
