Workbook

Sheet Journals
A1: Journal | B1: Tier | C1: Publisher | D1: Scope | E1: Quant Finance Relevance (1-5) | F1: ML Relevance (1-5) | G1: Recent Related Papers (IDs) | H1: Typical Methodology | I1: Empirical Expectations | J1: Theory Expectations | K1: Data Expectations | L1: Code / Data Policy | M1: Acceptance Difficulty (1-5) | N1: Fit Score (1-10) | O1: Priority Index (formula) | P1: Priority Rank (formula) | Q1: Target / Stretch / Backup | R1: OpenAlex 2-yr Mean Citedness (Sep 2026) | S1: OpenAlex h-index | T1: Clarivate JIF | U1: Notes
A2: Journal of Finance | B2: Tier 1 - General finance (top-3) | C2: Wiley / American Finance Association | D2: All areas of finance; publishes the field's most general contributions in asset pricing and investments. | E2: 4 | F2: 4 | G2: KMZ2024; JKX2023; KMP2023; BPZ2025; JKP2023; DMU2024; DNMV2023; MP2016; GP2013 | H2: Economically motivated empirical designs, often with a model or clear economic mechanism; ML accepted when it answers an economic question. | I2: Very long samples (decades), CRSP/Compustat standard, extensive robustness, international or out-of-sample replication increasingly common. | J2: Not strictly required, but a mechanism or theoretical framing strongly helps; pure horse races rarely suffice. | K2: Standard academic data (WRDS); proprietary data accepted if documented. | L2: Verified: AFA Data and Code Sharing Policy (April 2024 version) requires programs for replication from accepted empirical papers. | M2: 5 | N2: 7 | O2: =ROUND(0.6*N2+0.8*AVERAGE(E2:F2)-0.3*M2,2) | P2: =RANK(O2,$O$2:$O$29) | Q2: Stretch | R2: 13.19 | S2: 664 | T2: Not verified - check Clarivate JCR | U2: Fit only if the paper delivers a general economic insight (e.g., where ML value comes from and why) rather than a better backtest.
A3: Review of Financial Studies | B3: Tier 1 - General finance (top-3) | C3: Oxford University Press / Society for Financial Studies | D3: Broad financial economics; strong record in empirical asset pricing and ML (Gu-Kelly-Xiu 2020; JKMP 2026). | E3: 4 | F3: 5 | G3: GKX2020; JKMP2026; DMNU2020; FNW2020; HKS2020; NMV2016; LW2017; BS2022; HXZ2020; HLZ2016 | H3: Rigorous empirical asset pricing; ML papers must show economic content and robustness. | I3: Comprehensive samples, strong baselines, transaction costs expected for investment claims, replication package. | J3: Helpful; an economic framework or model of why the effect exists is expected for top placement. | K3: WRDS-standard; code and data package reviewed by Data Editors. | L3: Verified: updated Code and Data Sharing Policy for submissions conditionally accepted on/after 1 Oct 2025; Data Editors check reproducibility; deposit in Harvard Dataverse. | M3: 5 | N3: 8 | O3: =ROUND(0.6*N3+0.8*AVERAGE(E3:F3)-0.3*M3,2) | P3: =RANK(O3,$O$2:$O$29) | Q3: Stretch | R3: 11.81 | S3: 397 | T3: Not verified - check Clarivate JCR | U3: Most natural top-3 home for an implementability/decomposition paper given GKX2020, DMNU2020 and JKMP2026 precedents.
A4: Journal of Financial Economics | B4: Tier 1 - General finance (top-3) | C4: Elsevier | D4: Financial economics broadly; empirical and theoretical. | E4: 3 | F4: 4 | G4: KPS2019; KNS2020; LWZ2022; CDS2020; CFHH2025; DM2016; PW2020; SYY2012 | H4: Economic mechanism-driven empirical work. | I4: Long samples, identification of economic channel, robustness. | J4: Mechanism expected. | K4: WRDS-standard. | L4: Policy page exists (jfinec.com/data-and-code-sharing-policy); details verify. | M4: 5 | N4: 6 | O4: =ROUND(0.6*N4+0.8*AVERAGE(E4:F4)-0.3*M4,2) | P4: =RANK(O4,$O$2:$O$29) | Q4: Stretch | R4: 12.37 | S4: 557 | T4: Not verified - check Clarivate JCR | U4: Less natural for methods-heavy portfolio construction papers than RFS/MS.
A5: Journal of Financial and Quantitative Analysis | B5: Tier 1b - Top field finance | C5: Cambridge University Press / U. Washington | D5: Verified (jfqa.org): theoretical and empirical research in financial economics, including investments, capital and security markets, and quantitative methods of particular relevance to financial researchers. | E5: 5 | F5: 4 | G5: CV2023; KO2012; KZ2007 | H5: Rigorous empirical and quantitative methods; explicitly welcomes quantitative methods. | I5: Comparable to top-3 in rigor; somewhat narrower contribution acceptable. | J5: Not required for empirical methods papers with clear economic implications. | K5: WRDS-standard. | L5: Verified: JFQA Code Sharing Policy page exists; details verify. | M5: 4 | N5: 9 | O5: =ROUND(0.6*N5+0.8*AVERAGE(E5:F5)-0.3*M5,2) | P5: =RANK(O5,$O$2:$O$29) | Q5: Target | R5: 3.39 | S5: 255 | T5: Not verified - check Clarivate JCR | U5: Best realistic high-quality target: quantitative methods mandate plus finance audience.
A6: Management Science | B6: Tier 1b - Top field finance / OR | C6: INFORMS | D6: Management broadly; Finance department publishes empirical asset pricing and ML (Chen-Pelger-Zhu 2024; Avramov-Cheng-Metzker 2023). | E6: 4 | F6: 5 | G6: CPZ2024; ACM2023; EG2022; BCZ2022 | H6: Methodological innovation with managerial/economic relevance; interdisciplinary ML/OR welcome. | I6: Strong out-of-sample and robustness; replication package reviewed. | J6: Not required; methodological or economic insight required. | K6: WRDS-standard; must be disclosable per policy. | L6: Verified: Code and Data Disclosure Policy adopted 2019 with a Data Editor who verifies replicability. | M6: 4 | N6: 9 | O6: =ROUND(0.6*N6+0.8*AVERAGE(E6:F6)-0.3*M6,2) | P6: =RANK(O6,$O$2:$O$29) | Q6: Target | R6: 6.23 | S6: 480 | T6: Not verified - check Clarivate JCR | U6: Strong fit for a design that bridges ML, optimisation and finance.
A7: Review of Finance | B7: Tier 1b - Top field finance | C7: Oxford University Press / European Finance Association | D7: General finance (European Finance Association journal). | E7: 3 | F7: 3 | G7: (search for recent ML asset-pricing papers before targeting) | H7: General finance standards. | I7: High. | J7: Helpful. | K7: Standard. | L7: Verified: Code Sharing and Data Availability Policy page exists (revfin.org). | M7: 4 | N7: 7 | O7: =ROUND(0.6*N7+0.8*AVERAGE(E7:F7)-0.3*M7,2) | P7: =RANK(O7,$O$2:$O$29) | Q7: Target | R7: n/a | S7: n/a | T7: Not verified - check Clarivate JCR | U7: OpenAlex search did not return this title cleanly; verify metrics.
A8: Review of Asset Pricing Studies | B8: Tier 1b - Top field finance | C8: Oxford University Press / SFS | D8: Asset pricing (SFS field journal). | E8: 4 | F8: 4 | G8: KNNV2024 | H8: Asset-pricing empirical and theory. | I8: High. | J8: Helpful. | K8: WRDS-standard. | L8: SFS journal; verify policy. | M8: 4 | N8: 8 | O8: =ROUND(0.6*N8+0.8*AVERAGE(E8:F8)-0.3*M8,2) | P8: =RANK(O8,$O$2:$O$29) | Q8: Target | R8: 4.3 | S8: 49 | T8: Not verified - check Clarivate JCR | U8: Good home for factor-timing / signal-efficacy concepts.
A9: Operations Research | B9: Tier 1b - Top OR | C9: INFORMS | D9: OR methods incl. financial engineering; robust and data-driven optimisation. | E9: 3 | F9: 4 | G9: DY2010 | H9: Novel optimisation/learning methodology with guarantees. | I9: Computational experiments; finance data used as application. | J9: Usually expected (algorithms, guarantees). | K9: Flexible. | L9: Verify. | M9: 5 | N9: 5 | O9: =ROUND(0.6*N9+0.8*AVERAGE(E9:F9)-0.3*M9,2) | P9: =RANK(O9,$O$2:$O$29) | Q9: Backup (method variant) | R9: 3.48 | S9: 304 | T9: Not verified - check Clarivate JCR | U9: Only for the differentiable/robust optimiser concept with theoretical results.
A10: Quantitative Finance | B10: Tier 2 - Quantitative/computational finance | C10: Taylor & Francis | D10: Interdisciplinary quantitative finance; aims list includes portfolio management, market dynamics and prediction, trading systems, financial econometrics, market microstructure. | E10: 5 | F10: 4 | G10: BK2023; CI2023; NML2018 | H10: Quantitative/mathematical methods with empirical validation. | I10: Moderate-to-high; costs expected for trading claims. | J10: Welcome, not mandatory. | K10: Flexible. | L10: Verify. | M10: 3 | N10: 9 | O10: =ROUND(0.6*N10+0.8*AVERAGE(E10:F10)-0.3*M10,2) | P10: =RANK(O10,$O$2:$O$29) | Q10: Target | R10: 2.46 | S10: 113 | T10: Not verified - check Clarivate JCR | U10: Third-party sites report a 2025 JIF around 1.9 (unverified; check JCR).
A11: Journal of Financial Econometrics | B11: Tier 2 - Quantitative/computational finance | C11: Oxford University Press / SoFiE | D11: Financial econometrics. | E11: 5 | F11: 4 | G11: (verify recent ML papers) | H11: Econometric rigor; inference emphasis. | I11: High for inference. | J11: Econometric theory valued. | K11: Flexible. | L11: Verify. | M11: 4 | N11: 7 | O11: =ROUND(0.6*N11+0.8*AVERAGE(E11:F11)-0.3*M11,2) | P11: =RANK(O11,$O$2:$O$29) | Q11: Target (inference-heavy variant) | R11: 1.22 | S11: 77 | T11: Not verified - check Clarivate JCR | U11: Fits if inference framework (SPA/MCS for decomposition) is a core contribution.
A12: Journal of Econometrics | B12: Tier 2 - Econometrics (top) | C12: Elsevier | D12: Econometric methodology. | E12: 3 | F12: 4 | G12: GKX2021; CW2007; KP2015 | H12: New econometric methods with theory. | I12: Application. | J12: Required. | K12: Flexible. | L12: Verify. | M12: 5 | N12: 4 | O12: =ROUND(0.6*N12+0.8*AVERAGE(E12:F12)-0.3*M12,2) | P12: =RANK(O12,$O$2:$O$29) | Q12: Not recommended (unless new estimator) | R12: 2.95 | S12: 333 | T12: Not verified - check Clarivate JCR | U12: Needs formal econometric contribution.
A13: Journal of Business & Economic Statistics | B13: Tier 2 - Econometrics | C13: Taylor & Francis / ASA | D13: Applied statistics and econometrics. | E13: 3 | F13: 4 | G13: HAN2005; DM1995 | H13: Statistical methods with applications. | I13: Moderate. | J13: Often. | K13: Flexible. | L13: Verify. | M13: 4 | N13: 5 | O13: =ROUND(0.6*N13+0.8*AVERAGE(E13:F13)-0.3*M13,2) | P13: =RANK(O13,$O$2:$O$29) | Q13: Backup (inference variant) | R13: 1.86 | S13: 234 | T13: Not verified - check Clarivate JCR
A14: International Journal of Forecasting | B14: Tier 2 - Forecasting | C14: Elsevier / International Institute of Forecasters | D14: Forecasting methods and evaluation, incl. forecast combination. | E14: 3 | F14: 5 | G14: (forecast combination literature) | H14: Forecast evaluation rigor; combination methods. | I14: Moderate-high. | J14: Optional. | K14: Flexible. | L14: Verify. | M14: 3 | N14: 7 | O14: =ROUND(0.6*N14+0.8*AVERAGE(E14:F14)-0.3*M14,2) | P14: =RANK(O14,$O$2:$O$29) | Q14: Target (combination-focused variant) | R14: 3.79 | S14: 188 | T14: Not verified - check Clarivate JCR | U14: Fits a dynamic forecast-combination paper; must still show economic value.
A15: European Journal of Operational Research | B15: Tier 2 - OR (high-volume) | C15: Elsevier | D15: OR incl. financial modelling and portfolio optimisation. | E15: 4 | F15: 5 | G15: FK2018; KDH2017; BAMS2014 | H15: OR/ML methods with finance applications. | I15: Moderate; transaction costs increasingly expected. | J15: Optional. | K15: Flexible. | L15: Verify. | M15: 3 | N15: 7 | O15: =ROUND(0.6*N15+0.8*AVERAGE(E15:F15)-0.3*M15,2) | P15: =RANK(O15,$O$2:$O$29) | Q15: Backup | R15: 5.86 | S15: 407 | T15: Not verified - check Clarivate JCR | U15: Good for optimisation-heavy variants.
A16: Journal of Banking & Finance | B16: Tier 2 - Field finance | C16: Elsevier | D16: Finance and banking broadly, incl. investments. | E16: 4 | F16: 3 | G16: MPR2026 | H16: Empirical finance. | I16: High. | J16: Optional. | K16: WRDS-standard. | L16: Verify. | M16: 3 | N16: 8 | O16: =ROUND(0.6*N16+0.8*AVERAGE(E16:F16)-0.3*M16,2) | P16: =RANK(O16,$O$2:$O$29) | Q16: Backup (strong) | R16: 4.45 | S16: 309 | T16: Not verified - check Clarivate JCR
A17: Journal of Empirical Finance | B17: Tier 2 - Field finance | C17: Elsevier | D17: Empirical finance and financial econometrics. | E17: 4 | F17: 3 | G17: LW2008 | H17: Empirical/econometric. | I17: High. | J17: Optional. | K17: WRDS-standard. | L17: Verify. | M17: 3 | N17: 8 | O17: =ROUND(0.6*N17+0.8*AVERAGE(E17:F17)-0.3*M17,2) | P17: =RANK(O17,$O$2:$O$29) | Q17: Backup (strong) | R17: 2.82 | S17: 133 | T17: Not verified - check Clarivate JCR
A18: Journal of Financial Markets | B18: Tier 2 - Field finance | C18: Elsevier | D18: Market microstructure, trading, asset pricing. | E18: 5 | F18: 3 | G18: TH2021; WL2025; AMI2002 | H18: Empirical microstructure / trading. | I18: High for cost modelling. | J18: Optional. | K18: TAQ/WRDS. | L18: Verify. | M18: 3 | N18: 8 | O18: =ROUND(0.6*N18+0.8*AVERAGE(E18:F18)-0.3*M18,2) | P18: =RANK(O18,$O$2:$O$29) | Q18: Backup (strong) | R18: 2.09 | S18: 104 | T18: Not verified - check Clarivate JCR | U18: Natural home if transaction-cost modelling is central.
A19: Journal of Economic Dynamics and Control | B19: Tier 2 - Field | C19: Elsevier | D19: Computational economics and finance. | E19: 3 | F19: 3 | G19: CFMZ2023; GT2007 | H19: Computational/empirical. | I19: Moderate-high. | J19: Optional. | K19: Flexible. | L19: Verify. | M19: 3 | N19: 6 | O19: =ROUND(0.6*N19+0.8*AVERAGE(E19:F19)-0.3*M19,2) | P19: =RANK(O19,$O$2:$O$29) | Q19: Backup | R19: 2 | S19: 168 | T19: Not verified - check Clarivate JCR
A20: Critical Finance Review | B20: Tier 2 - Field (replication/critique) | C20: Now Publishers | D20: Critical/replication-oriented finance research. | E20: 4 | F20: 3 | G20: LEW2015; CZ2022 | H20: Replication, critique, careful re-examination. | I20: High transparency. | J20: Optional. | K20: Open where possible. | L20: Verify. | M20: 3 | N20: 7 | O20: =ROUND(0.6*N20+0.8*AVERAGE(E20:F20)-0.3*M20,2) | P20: =RANK(O20,$O$2:$O$29) | Q20: Backup (if results are mainly a critical re-assessment) | R20: 3.74 | S20: 32 | T20: Not verified - check Clarivate JCR
A21: Mathematical Finance | B21: Tier 2 - Mathematical finance | C21: Wiley | D21: Mathematical finance theory. | E21: 3 | F21: 2 | G21: - | H21: Mathematical theory. | I21: Low. | J21: Required. | K21: - | L21: Verify. | M21: 5 | N21: 2 | O21: =ROUND(0.6*N21+0.8*AVERAGE(E21:F21)-0.3*M21,2) | P21: =RANK(O21,$O$2:$O$29) | Q21: Not recommended | R21: 1.6 | S21: 129 | T21: Not verified - check Clarivate JCR | U21: Poor fit for empirical signal combination.
A22: Journal of Computational Finance | B22: Tier 2 - Computational finance | C22: Infopro Digital (Risk.net) | D22: Verified (risk.net): numerical and computational techniques in pricing, hedging and risk management; recent issues include ML and portfolio optimisation. | E22: 3 | F22: 3 | G22: BBLZ2017 | H22: Numerical methods. | I22: Low-moderate. | J22: Numerical analysis. | K22: - | L22: Verify. | M22: 3 | N22: 4 | O22: =ROUND(0.6*N22+0.8*AVERAGE(E22:F22)-0.3*M22,2) | P22: =RANK(O22,$O$2:$O$29) | Q22: Not recommended (except optimiser-computation variant) | R22: 0.68 | S22: 57 | T22: Not verified - check Clarivate JCR | U22: Editor-in-chief: Christoph Reisinger (risk.net).
A23: Annals of Operations Research | B23: Tier 2/3 - OR | C23: Springer | D23: OR applications incl. finance. | E23: 3 | F23: 4 | G23: ULM2024; SYM2025 | H23: OR/ML. | I23: Moderate. | J23: Optional. | K23: Flexible. | L23: Verify. | M23: 2 | N23: 6 | O23: =ROUND(0.6*N23+0.8*AVERAGE(E23:F23)-0.3*M23,2) | P23: =RANK(O23,$O$2:$O$29) | Q23: Backup | R23: 3.89 | S23: 186 | T23: Not verified - check Clarivate JCR
A24: Financial Analysts Journal | B24: Tier 3 - Practitioner (high reputation) | C24: Taylor & Francis / CFA Institute | D24: Practitioner-relevant investment research. | E24: 4 | F24: 4 | G24: RJ2019; KPT2012; NMV2019; LO2002; BL1992 | H24: Rigorous but accessible. | I24: Practical relevance, costs, capacity. | J24: Not required. | K24: Flexible. | L24: Verify. | M24: 3 | N24: 7 | O24: =ROUND(0.6*N24+0.8*AVERAGE(E24:F24)-0.3*M24,2) | P24: =RANK(O24,$O$2:$O$29) | Q24: Backup (practitioner version) | R24: 2.74 | S24: 168 | T24: Not verified - check Clarivate JCR | U24: Shorter practitioner spin-off of the main paper.
A25: Journal of Portfolio Management | B25: Tier 3 - Practitioner | C25: With Intelligence (PMR) | D25: Practitioner portfolio management. | E25: 4 | F25: 3 | G25: BLDP2014; LDP2016; HL2015; CSS2012; LS2008 | H25: Practitioner. | I25: Moderate. | J25: No. | K25: Flexible. | L25: None known. | M25: 2 | N25: 6 | O25: =ROUND(0.6*N25+0.8*AVERAGE(E25:F25)-0.3*M25,2) | P25: =RANK(O25,$O$2:$O$29) | Q25: Backup (practitioner) | R25: 0.8 | S25: 116 | T25: Not verified - check Clarivate JCR
A26: Journal of Financial Data Science | B26: Tier 3 - Practitioner ML | C26: With Intelligence (PMR) | D26: Data science and ML in finance for practitioners. | E26: 4 | F26: 5 | G26: BHHH2023; LLMSS2021; ZZR2020; LZR2019; AHM2019 | H26: Applied ML. | I26: Moderate. | J26: No. | K26: Flexible. | L26: None known. | M26: 2 | N26: 6 | O26: =ROUND(0.6*N26+0.8*AVERAGE(E26:F26)-0.3*M26,2) | P26: =RANK(O26,$O$2:$O$29) | Q26: Backup (practitioner ML) | R26: 0.68 | S26: 21 | T26: Not verified - check Clarivate JCR
A27: ACM ICAIF (conference) | B27: ML/AI venue - finance-specific | C27: ACM | D27: Verified: ACM International Conference on AI in Finance, proceedings in ACM DL (2020-2025; 2026 in Milan). | E27: 3 | F27: 5 | G27: - | H27: AI/ML methods. | I27: Benchmarks; costs often lighter. | J27: Optional. | K27: Public benchmarks favoured. | L27: Varies. | M27: 2 | N27: 5 | O27: =ROUND(0.6*N27+0.8*AVERAGE(E27:F27)-0.3*M27,2) | P27: =RANK(O27,$O$2:$O$29) | Q27: Early dissemination | R27: n/a | S27: n/a | T27: Not verified - check Clarivate JCR | U27: Useful for feedback on ML components; limited weight for finance hiring/promotion.
A28: NeurIPS / ICML / KDD (main or workshops) | B28: ML/AI venue - general | C28: Various | D28: General ML; finance appears in applications and workshops. | E28: 2 | F28: 5 | G28: DAK2017; AK2017; AAB2019; DA2023 | H28: ML novelty. | I28: ML benchmarks. | J28: Often. | K28: Public. | L28: Code often expected. | M28: 4 | N28: 3 | O28: =ROUND(0.6*N28+0.8*AVERAGE(E28:F28)-0.3*M28,2) | P28: =RANK(O28,$O$2:$O$29) | Q28: Not recommended for main paper | R28: n/a | S28: n/a | T28: Not verified - check Clarivate JCR | U28: Finance reviewers discount these unless economic evaluation is rigorous.
A29: Expert Systems with Applications | B29: Tier 3 - Applied AI (high-volume) | C29: Elsevier | D29: Applied intelligent systems. | E29: 2 | F29: 5 | G29: - | H29: Applied ML. | I29: Variable; costs often omitted. | J29: No. | K29: Flexible. | L29: Verify. | M29: 2 | N29: 3 | O29: =ROUND(0.6*N29+0.8*AVERAGE(E29:F29)-0.3*M29,2) | P29: =RANK(O29,$O$2:$O$29) | Q29: Not recommended | R29: 7.51 | S29: 349 | T29: Not verified - check Clarivate JCR | U29: High citation counts do not translate into finance-field reputation; illustrates why IF alone is misleading.

Sheet Summary
A1: Journal strategy summary (live formulas)
A2: Priority Index = 0.6*Fit + 0.8*mean(QF, ML relevance) - 0.3*Difficulty (team heuristic)
A4: Role | B4: Journals | C4: Avg fit
A5: Stretch | B5: =COUNTIF(Journals!$Q:$Q,"*Stretch*") | C5: =IFERROR(ROUND(AVERAGEIF(Journals!$Q:$Q,"*Stretch*",Journals!$N:$N),2),"")
A6: Target | B6: =COUNTIF(Journals!$Q:$Q,"*Target*") | C6: =IFERROR(ROUND(AVERAGEIF(Journals!$Q:$Q,"*Target*",Journals!$N:$N),2),"")
A7: Backup | B7: =COUNTIF(Journals!$Q:$Q,"*Backup*") | C7: =IFERROR(ROUND(AVERAGEIF(Journals!$Q:$Q,"*Backup*",Journals!$N:$N),2),"")
A8: Not recommended | B8: =COUNTIF(Journals!$Q:$Q,"*Not recommended*") | C8: =IFERROR(ROUND(AVERAGEIF(Journals!$Q:$Q,"*Not recommended*",Journals!$N:$N),2),"")
A9: Practitioner | B9: =COUNTIF(Journals!$Q:$Q,"*Practitioner*") | C9: =IFERROR(ROUND(AVERAGEIF(Journals!$Q:$Q,"*Practitioner*",Journals!$N:$N),2),"")
A10: Early dissemination | B10: =COUNTIF(Journals!$Q:$Q,"*Early dissemination*") | C10: =IFERROR(ROUND(AVERAGEIF(Journals!$Q:$Q,"*Early dissemination*",Journals!$N:$N),2),"")
A13: Tier | B13: Journals | C13: Avg fit | D13: Avg difficulty
A14: ML/AI venue - finance-specific | B14: =COUNTIF(Journals!$B:$B,$A14) | C14: =IFERROR(ROUND(AVERAGEIF(Journals!$B:$B,$A14,Journals!$N:$N),2),"") | D14: =IFERROR(ROUND(AVERAGEIF(Journals!$B:$B,$A14,Journals!$M:$M),2),"")
A15: ML/AI venue - general | B15: =COUNTIF(Journals!$B:$B,$A15) | C15: =IFERROR(ROUND(AVERAGEIF(Journals!$B:$B,$A15,Journals!$N:$N),2),"") | D15: =IFERROR(ROUND(AVERAGEIF(Journals!$B:$B,$A15,Journals!$M:$M),2),"")
A16: Tier 1 - General finance (top-3) | B16: =COUNTIF(Journals!$B:$B,$A16) | C16: =IFERROR(ROUND(AVERAGEIF(Journals!$B:$B,$A16,Journals!$N:$N),2),"") | D16: =IFERROR(ROUND(AVERAGEIF(Journals!$B:$B,$A16,Journals!$M:$M),2),"")
A17: Tier 1b - Top OR | B17: =COUNTIF(Journals!$B:$B,$A17) | C17: =IFERROR(ROUND(AVERAGEIF(Journals!$B:$B,$A17,Journals!$N:$N),2),"") | D17: =IFERROR(ROUND(AVERAGEIF(Journals!$B:$B,$A17,Journals!$M:$M),2),"")
A18: Tier 1b - Top field finance | B18: =COUNTIF(Journals!$B:$B,$A18) | C18: =IFERROR(ROUND(AVERAGEIF(Journals!$B:$B,$A18,Journals!$N:$N),2),"") | D18: =IFERROR(ROUND(AVERAGEIF(Journals!$B:$B,$A18,Journals!$M:$M),2),"")
A19: Tier 1b - Top field finance / OR | B19: =COUNTIF(Journals!$B:$B,$A19) | C19: =IFERROR(ROUND(AVERAGEIF(Journals!$B:$B,$A19,Journals!$N:$N),2),"") | D19: =IFERROR(ROUND(AVERAGEIF(Journals!$B:$B,$A19,Journals!$M:$M),2),"")
A20: Tier 2 - Computational finance | B20: =COUNTIF(Journals!$B:$B,$A20) | C20: =IFERROR(ROUND(AVERAGEIF(Journals!$B:$B,$A20,Journals!$N:$N),2),"") | D20: =IFERROR(ROUND(AVERAGEIF(Journals!$B:$B,$A20,Journals!$M:$M),2),"")
A21: Tier 2 - Econometrics | B21: =COUNTIF(Journals!$B:$B,$A21) | C21: =IFERROR(ROUND(AVERAGEIF(Journals!$B:$B,$A21,Journals!$N:$N),2),"") | D21: =IFERROR(ROUND(AVERAGEIF(Journals!$B:$B,$A21,Journals!$M:$M),2),"")
A22: Tier 2 - Econometrics (top) | B22: =COUNTIF(Journals!$B:$B,$A22) | C22: =IFERROR(ROUND(AVERAGEIF(Journals!$B:$B,$A22,Journals!$N:$N),2),"") | D22: =IFERROR(ROUND(AVERAGEIF(Journals!$B:$B,$A22,Journals!$M:$M),2),"")
A23: Tier 2 - Field | B23: =COUNTIF(Journals!$B:$B,$A23) | C23: =IFERROR(ROUND(AVERAGEIF(Journals!$B:$B,$A23,Journals!$N:$N),2),"") | D23: =IFERROR(ROUND(AVERAGEIF(Journals!$B:$B,$A23,Journals!$M:$M),2),"")
A24: Tier 2 - Field (replication/critique) | B24: =COUNTIF(Journals!$B:$B,$A24) | C24: =IFERROR(ROUND(AVERAGEIF(Journals!$B:$B,$A24,Journals!$N:$N),2),"") | D24: =IFERROR(ROUND(AVERAGEIF(Journals!$B:$B,$A24,Journals!$M:$M),2),"")
A25: Tier 2 - Field finance | B25: =COUNTIF(Journals!$B:$B,$A25) | C25: =IFERROR(ROUND(AVERAGEIF(Journals!$B:$B,$A25,Journals!$N:$N),2),"") | D25: =IFERROR(ROUND(AVERAGEIF(Journals!$B:$B,$A25,Journals!$M:$M),2),"")
... A34: Tier 3 - Practitioner ML | B34: =COUNTIF(Journals!$B:$B,$A34) | C34: =IFERROR(ROUND(AVERAGEIF(Journals!$B:$B,$A34,Journals!$N:$N),2),"") | D34: =IFERROR(ROUND(AVERAGEIF(Journals!$B:$B,$A34,Journals!$M:$M),2),"")

Sheet Metrics_Note
A1: About the metrics
A2: Read before quoting any number
A4: OpenAlex 2-year mean citedness and h-index were retrieved from api.openalex.org/sources in September 2026 (raw JSON in 02_Journal_Strategy).
A5: OpenAlex 2-year mean citedness is an open analogue of an impact factor but is NOT the Clarivate Journal Impact Factor.
A6: Clarivate JIF values were not verified from an accessible primary source and are intentionally left blank.
A7: Chartered ABS AJG and ABDC ratings should be checked on the official lists before use.
A8: Relevance, difficulty and fit scores are team judgements for this specific project, not journal-quality ratings.
A9: Code/data policy entries marked 'Verified' were confirmed on the journal or association policy page.
