Workbook

Sheet Literature
A1: Paper ID | B1: Title | C1: Authors | D1: Year | E1: Journal | F1: Journal Tier | G1: DOI / URL | H1: Strand | I1: Core paper? | J1: Research Question | K1: Data | L1: Universe | M1: Frequency | N1: Features | O1: ML Method | P1: Signal Method | Q1: Portfolio Method | R1: Benchmark | S1: Evaluation Metrics | T1: Backtest Period | U1: Transaction Costs | V1: Turnover | W1: Risk Controls | X1: Performance (main result) | Y1: Main Contribution | Z1: Main Limitation | AA1: What Was Not Solved | AB1: Research Gap | AC1: Potential Extension | AD1: Relevance to Us (1-5) | AE1: How We Use It / Note | AF1: DOI Verification Status
A2: JKMP2026 | B2: Machine Learning and the Implementable Efficient Frontier | C2: Jensen, T.I.; Kelly, B.; Malamud, S.; Pedersen, L.H. | D2: 2026 | E2: Review of Financial Studies (published online 2026) | F2: T1 General Finance | G2: https://doi.org/10.1093/rfs/hhag022 | H2: ML strategies & implementability | I2: Yes | J2: How should ML be used so that portfolios deliver the best risk-return trade-off net of trading costs? | K2: JKP global characteristics dataset (US monthly characteristics, daily and monthly returns); WRDS access required (code README) | L2: US stocks | M2: Monthly characteristics; daily returns for risk estimation | N2: JKP firm characteristics (about 150, clustered into 13 themes) | O2: Ridge-type regressions on random Fourier features; separate models for returns at horizons t+1..t+12 (code README) | P2: Learned jointly with the portfolio objective in Portfolio-ML; prediction-first in Markowitz-ML / Static-ML | Q2: Trading-cost-aware optimisation; methods compared: Portfolio-ML, Static-ML, Static-ML*, Markowitz-ML, portfolio sorts | R2: Markowitz-ML, portfolio sort, 1/N, market [verify full list] | S2: Implementable efficient frontier (net return per unit of risk), net Sharpe ratio, utility, economic feature importance | T2: US out-of-sample period [verify dates] | U2: Explicit trading-cost model entering the optimisation (price impact increasing in trade size relative to liquidity) [verify calibration] | V2: Controlled endogenously through the cost-aware objective | W2: Covariance estimate inside the mean-variance utility | X2: After costs, Markowitz-ML and sorts have downward-bending frontiers; Static-ML earns positive net Sharpe but negative utility unless tuned; Portfolio-ML, which learns weights under an economic objective, works best out of sample. | Y2: Moved ML evaluation from gross prediction to the implementable frontier; introduced economic feature importance. | Z2: [inference] The paper's focus is the cost-aware objective; explicit state- or regime-dependence of signal weights and forecast uncertainty are not its central questions (verify in full text). | AA2: [inference] How much of the net gain comes from nonlinearity versus conditioning versus the objective; whether conditioning on market states adds value once costs are internalised. | AB2: Closest prior art for any cost-aware ML combination claim | AC2: Use Portfolio-ML as the strongest benchmark and nest it inside a factorial decomposition [inference]. | AD2: 5 | AE2: Detailed core entry | AF2: DOI from publisher page/search; Crossref-confirmed
A3: SWZ2023 | B3: Deep Parametric Portfolio Policies | C3: Simon, F.; Weibels, S.; Zimmermann, T. | D3: 2026 | E3: Management Science (2026; Crossref record) - earlier CFR Working Paper 23-01 / SSRN 4150292 | F3: T1b Finance/OR | G3: https://doi.org/10.1287/mnsc.2025.00721 | H3: End-to-end / decision-focused | I3: Yes | J3: Do neural-network parametric portfolio policies beat linear policies? | K3: US equities with firm characteristics [verify] | L3: US stocks | M3: Monthly | N3: Firm characteristics | O3: Feed-forward neural networks mapping characteristics to weight tilts | P3: Learned directly from utility | Q3: Deep parametric portfolio policy with weight/leverage constraints | R3: Linear parametric portfolio policy | S3: Certainty-equivalent returns | T3: [verify] | U3: Incorporated; results robust after costs [verify whether costs enter training] | V3: [verify] | W3: Utility functions | X3: Network-based policies achieve 75-276 bps higher monthly certainty-equivalent returns than a comparable linear policy, robust to costs and short-sale restrictions. | Y3: Nonlinear generalisation of PPP under an economic objective. | Z3: Static mapping; state dependence and uncertainty not central [inference]. | AA3: Decomposition of gains; state conditioning. | AB3: Close prior art (nonlinear economic-objective learning) | AC3: Benchmark column; nonlinear-objective cell [inference]. | AD3: 5 | AE3: Detailed core entry | AF3: DOI from publisher page/search; Crossref-confirmed
A4: LMNS2025 | B4: The Uncertainty of Machine Learning Predictions in Asset Pricing | C4: Liao, Y.; Ma, X.; Neuhierl, A.; Schilling, L. | D4: 2025 | E4: Working paper (arXiv 2503.00549) | F4: WP | G4: https://arxiv.org/abs/2503.00549 | H4: ML asset pricing | I4: Yes | J4: How uncertain are neural-network expected-return forecasts, and does accounting for it improve portfolios? | K4: Equity panel [verify] | L4: [verify] | M4: Monthly | N4: Firm characteristics | O4: Neural networks; closed-form and bootstrap standard errors | P4: Forecast confidence intervals | Q4: Uncertainty-averse investment framework (shrinkage interpretation) | R4: Point-forecast portfolios | S4: Out-of-sample performance | T4: [verify] | U4: [verify] | V4: [verify] | W4: Uncertainty aversion | X4: NN return forecasts share the asymptotic distribution of classic nonparametric estimators, giving closed-form standard errors; using the intervals improves out-of-sample performance. | Y4: Formal inference for ML expected returns and its portfolio use. | Z4: Working paper; cost interaction not central [inference]. | AA4: Interaction of uncertainty with trading costs and state dependence. | AB4: Close prior art (uncertainty) | AC4: Use as the uncertainty cell and closest prior art for Concept 3 [inference]. | AD4: 5 | AE4: Detailed core entry | AF4: Working paper (journal DOI not available/verified)
A5: CHK2024 | B5: Design Choices, Machine Learning, and the Cross-Section of Stock Returns | C5: Chen, M.; Hanauer, M.X.; Kalsbach, T. | D5: 2024 | E5: Working paper (SSRN 5031755) | F5: WP | G5: https://ssrn.com/abstract=5031755 | H5: ML strategies & implementability | I5: Yes | J5: How much do researcher design choices change ML-based return-prediction portfolios? | K5: US equities with anomaly inputs | L5: US stocks, with/without microcaps | M5: Monthly | N5: Anomaly characteristics; with/without compression; pre-publication-only variants | O5: Multiple ML models across 1,056 design combinations | P5: Varies by design | Q5: Top-minus-bottom portfolios | R5: Across-design distribution | S5: Mean top-minus-bottom returns; non-standard errors | T5: [verify] | U5: [verify] | V5: [verify] | W5: n/a | X5: Seven design choices (model, target, target transformation, pre-publication inputs, feature compression, rolling vs expanding window, microcaps) generate monthly top-minus-bottom returns from 0.13% to 1.98%; the non-standard error exceeds the standard error by 59%. | Y5: Quantified non-standard errors in ML asset-pricing research. | Z5: Documents dispersion; not a combination method. | AA5: Which choices create net-of-cost value and why. | AB5: Methodological robustness standard | AC5: Adopt multiverse reporting for our design [inference]. | AD5: 5 | AE5: Detailed core entry | AF5: Working paper (journal DOI not available/verified)
A6: DMU2024 | B6: A Multifactor Perspective on Volatility-Managed Portfolios | C6: DeMiguel, V.; Martin-Utrera, A.; Uppal, R. | D6: 2024 | E6: Journal of Finance 79:3859-3891 | F6: T1 General Finance | G6: https://doi.org/10.1111/jofi.13395 | H6: Factor timing & regimes | I6: Yes | J6: Can conditioning factor weights on volatility add value out of sample and net of costs in a multifactor setting? | K6: US factor portfolios; replication package on Mendeley Data | L6: Factor portfolios | M6: Monthly | N6: Factor volatilities | O6: n/a | P6: Conditional multifactor weights | Q6: Conditional multifactor portfolio | R6: Unconditional multifactor and single-factor volatility-managed portfolios | S6: Out-of-sample Sharpe net of costs | T6: [verify] | U6: Explicit | V6: Explicit | W6: Mean-variance | X6: Single-factor volatility management does not survive costs, but a conditional multifactor portfolio outperforms its unconditional counterpart out of sample and net of costs; factor risk prices generally fall with market volatility. | Y6: Evidence that state-conditional combination can survive costs when done jointly across factors. | Z6: Low-dimensional factor set; one conditioning variable family. | AA6: Stock-level, high-dimensional, nonlinear conditioning. | AB6: State conditioning in low dimension | AC6: Generalise conditioning to many states and signals at stock level [inference]. | AD6: 5 | AE6: Detailed core entry | AF6: DOI from publisher page/search; Crossref-confirmed
A7: NRRZ2024 | B7: Timing the Factor Zoo | C7: Neuhierl, A.; Randl, O.; Reschenhofer, C.; Zechner, J. | D7: 2024 | E7: Working paper (SSRN 4376898); AFA/AEA conference programmes | F7: WP | G7: https://papers.ssrn.com/sol3/papers.cfm?abstract_id=4376898 | H7: Factor timing & regimes | I7: Yes | J7: Can the returns of hundreds of equity factors be timed with a high-dimensional set of predictors? | K7: 300+ equity risk factors and a high-dimensional predictor set | L7: US factor portfolios | M7: Monthly | N7: Factor-specific and aggregate predictors (past factor returns, volatility, valuation, macro, etc.) | O7: Partial least squares and other dimension-reduction/shrinkage methods | P7: Timed factor weights | Q7: Timed multifactor portfolio | R7: Untimed multifactor portfolio | S7: Predictive R2, factor portfolio returns | T7: [verify] | U7: [verify treatment] | V7: [verify] | W7: [verify] | X7: Almost all factor groups can be timed, most for profitability and value; past factor returns and volatility are the best single predictors but PLS aggregation dominates; timing raises the multifactor portfolio return by about 20%. | Y7: Most comprehensive evidence that factor (signal) efficacy is predictable over time. | Z7: Operates at the factor-portfolio level; stock-level netting and implementable costs are not the focus [inference]. | AA7: Whether factor-timing information survives when combined at the stock level inside a cost-aware optimizer [inference]. | AB7: Factor-level, not stock-level implementation | AC7: Feed timing predictors as state variables into stock-level combination [inference]. | AD7: 5 | AE7: Detailed core entry | AF7: Working paper (journal DOI not available/verified)
A8: ACM2023 | B8: Machine Learning vs. Economic Restrictions: Evidence from Stock Return Predictability | C8: Avramov, D.; Cheng, S.; Metzker, L. | D8: 2023 | E8: Management Science 69(5):2587-2619 | F8: T1b Finance/OR | G8: https://doi.org/10.1287/mnsc.2022.4449 | H8: ML strategies & implementability | I8: Yes | J8: Do deep-learning return signals survive economic restrictions such as excluding microcaps, distressed firms and high-volatility episodes, and trading costs? | K8: US equities; ML models from the recent literature (neural networks, conditional autoencoder, IPCA, adversarial SDF) [verify full list] | L8: US common stocks, with subsamples excluding microcaps and distressed firms | M8: Monthly | N8: Firm characteristics as in the replicated ML models | O8: Deep learning / latent-factor ML models | P8: Model-implied expected returns / pricing-kernel weights | Q8: Long-short and tangency portfolios implied by the models | R8: Unrestricted ML portfolios versus restricted universes | S8: Returns, alphas, turnover, net returns | T8: Out-of-sample US sample [verify dates] | U8: Reasonable trading costs applied; performance deteriorates because of high turnover and extreme positions | V8: High; identified as the main source of cost drag | W8: Universe restrictions act as economic filters | X8: ML profitability comes from difficult-to-arbitrage stocks and high limits-to-arbitrage states; excluding microcaps, distressed stocks or high-volatility episodes considerably attenuates it; costs erode it further. | Y8: Showed that headline ML alpha is concentrated where it is least implementable. | Z8: Diagnoses the problem; does not propose a combination method that is implementable by design. | AA8: How to build ML signal combinations whose value survives restrictions and costs. | AB8: Implementability of ML alpha | AC8: Use its restrictions as the default universe and report results both with and without them [inference]. | AD8: 5 | AE8: Detailed core entry | AF8: DOI from publisher page/search; Crossref-confirmed
A9: AHV2023 | B9: The Expected Returns on Machine-Learning Strategies | C9: Azevedo, V.; Hoegner, C.; Velikov, M. | D9: 2023 | E9: Working paper (SSRN 4702406); AFA programme | F9: WP | G9: https://papers.ssrn.com/sol3/papers.cfm?abstract_id=4702406 | H9: ML strategies & implementability | I9: Yes | J9: What are the expected returns of ML anomaly-combination strategies after costs, post-publication decay and the modern high-liquidity era? | K9: US anomaly characteristics | L9: US stocks | M9: Monthly | N9: Published anomaly characteristics | O9: Range from simple to sophisticated ML, including LSTM | P9: ML combination of anomaly characteristics | Q9: Long-short, value-weighted variants | R9: Simple combinations; factor models | S9: Net returns, generalized net alpha | T9: Includes post-decimalization era | U9: Explicit effective-spread costs | V9: Above 50% for profitable strategies | W9: n/a | X9: Sophisticated ML strategies earn net out-of-sample returns up to 1.42% per month; an LSTM combination has a six-factor generalized net alpha of 1.20% (t = 3.46). | Y9: Most direct evidence that some ML combinations remain profitable after costs and decay. | Z9: Cost handling is ex post (evaluation), not inside learning [inference]. | AA9: Cost-aware learning and state dependence. | AB9: Ex-post cost evaluation | AC9: Replicate as a benchmark column in the factorial design [inference]. | AD9: 5 | AE9: Detailed core entry | AF9: Working paper (journal DOI not available/verified)
A10: BHHH2023 | B10: The Term Structure of Machine Learning Alpha | C10: Blitz, D.; Hanauer, M.X.; Hoogteijling, T.; Howard, C. | D10: 2023 | E10: Journal of Financial Data Science 5(4) 5(4):40-65 | F10: T3 Practitioner | G10: https://doi.org/10.3905/jfds.2023.1.135 | H10: ML strategies & implementability | I10: Yes | J10: Does ML alpha survive costs, and does training on longer prediction horizons help? | K10: US equities [verify] | L10: [verify] | M10: Monthly | N10: Firm characteristics | O10: Common ML models (trees, neural networks) [verify] | P10: Forecasts at 1-12 month horizons | Q10: Long-short portfolios with efficient trading rules | R10: 1-month-horizon models | S10: Gross and net alpha | T10: Full sample and 2004-2021 subperiod | U10: Explicit | V10: Much lower for long-horizon models | W10: n/a | X10: Common ML models have high full-sample gross alphas but net performance near zero after 2004; training on longer horizons (3, 6, 12 months) and efficient trading rules yields significantly positive net returns. | Y10: Showed horizon choice is a first-order lever for net ML alpha. | Z10: Horizon is fixed per model, not adapted to states or signals. | AA10: Signal-specific and state-specific horizons. | AB10: Cost-aware horizon design | AC10: Let horizon/decay enter the combination explicitly [inference]. | AD10: 5 | AE10: Detailed core entry | AF10: Crossref match (title, author, year, journal)
A11: CV2023 | B11: Zeroing In on the Expected Returns of Anomalies | C11: Chen, A.Y.; Velikov, M. | D11: 2023 | E11: Journal of Financial and Quantitative Analysis 58(3):968-1004 | F11: T1b Finance/OR | G11: https://doi.org/10.1017/s0022109022000874 | H11: TC & implementability | I11: Yes | J11: What is the expected return of anomaly strategies net of spreads, post-publication decay and modern trading technology? | K11: 204 anomalies; effective bid-ask spreads | L11: US stocks | M11: Monthly | N11: n/a | O11: n/a | P11: Individual anomalies and combinations | Q11: Long-short with cost mitigation | R11: Gross returns | S11: Net expected returns | T11: Includes post-2000s era | U11: Effective bid-ask spreads (high- and low-frequency estimates) | V11: Cost mitigation applied | W11: n/a | X11: Net of these effects, the average anomaly earns about 4 bps per month; cost mitigation works pre-publication but net returns are tiny afterward. | Y11: Calibrates realistic expectations for signal-level alpha. | Z11: Mostly single anomalies. | AA11: Whether combination/netting rescues the value. | AB11: Signal-level alpha is small after costs | AC11: Use its spread data and horizon to set the cost baseline [inference]. | AD11: 5 | AE11: Detailed core entry | AF11: Crossref match (title, author, year, journal)
A12: JKP2023 | B12: Is There a Replication Crisis in Finance? | C12: Jensen, T.I.; Kelly, B.; Pedersen, L.H. | D12: 2023 | E12: Journal of Finance 78(5):2465-2518 | F12: T1 General Finance | G12: https://doi.org/10.1111/jofi.13249 | H12: Replication & multiple testing | I12: Yes | J12: Do published factors replicate, and how should multiple testing be handled? | K12: 153 factors, 93 countries (jkpfactors.com; CC BY-NC 4.0; updated through Dec 2025) | L12: Global | M12: Monthly | N12: 153 characteristics in 13 themes | O12: Bayesian hierarchical model of factor alphas | P12: Theme clusters | Q12: Factor portfolios; tangency portfolio | R12: Frequentist multiple-testing corrections | S12: Replication rates, posterior alphas | T12: Long global sample | U12: Not central | V12: n/a | W12: n/a | X12: Most factors replicate, cluster into 13 themes (most in the tangency portfolio), work out of sample across 93 countries, and evidence is strengthened by the number of factors. | Y12: Global, documented signal dataset and a Bayesian view of the factor zoo. | Z12: Gross factor returns. | AA12: Implementable combination. | AB12: Data infrastructure | AC12: Theme-level attribution and international robustness [inference]. | AD12: 5 | AE12: Detailed core entry | AF12: DOI from publisher page/search; Crossref-confirmed
A13: CZ2022 | B13: Open Source Cross-Sectional Asset Pricing | C13: Chen, A.Y.; Zimmermann, T. | D13: 2022 | E13: Critical Finance Review 11(2):207-264 | F13: T2 Quant/Field | G13: https://doi.org/10.1561/104.00000112 | H13: Data & measurement | I13: Yes | J13: Can the cross-sectional predictor literature be reproduced with open code and data? | K13: 319 characteristics in the paper; website provides 209 firm-level signals (212 incl. 3 CRSP-based) through Dec 2024 | L13: US stocks | M13: Monthly (daily portfolio returns also available) | N13: Published predictors | O13: n/a | P13: n/a | Q13: Original-paper long-short portfolios | R13: Original t-statistics | S13: Reproduced t-statistics | T13: Varies by signal | U13: Not part of the paper [verify] | V13: n/a | W13: n/a | X13: 98% of clearly significant predictors reproduce with t > 1.96; slope of reproduced on original t-stats is 0.88 with R2 of 82%. | Y13: Open signal library usable as the backbone of a signal-combination study. | Z13: Some inputs require CRSP/Compustat/IBES licences. | AA13: n/a | AB13: Data infrastructure | AC13: Primary open signal source [inference]. | AD13: 5 | AE13: Detailed core entry | AF13: Crossref match (title, author, year, journal)
... A35: CFMZ2023 | B35: Machine Learning Goes Global: Cross-Sectional Return Predictability in International Stock Markets | C35: Cakici, N.; Fieberg, C.; Metko, D.; Zaremba, A. | D35: 2023 | E35: Journal of Economic Dynamics and Control 155:104725 | F35: T2 Quant/Field | G35: https://doi.org/10.1016/j.jedc.2023.104725 | H35: ML asset pricing | I35: Yes | J35: How does ML return predictability vary across 46 stock markets? | K35: 46 countries, 148 firm characteristics | L35: International stocks | M35: Monthly | N35: 148 characteristics | O35: Repertoire of ML models and their combination | P35: Model combinations | Q35: Long-short | R35: Individual models | S35: Returns, alphas | T35: [verify] | U35: [verify] | V35: [verify] | W35: n/a | X35: Predictability comes mainly from momentum, reversal, value and size; combining models is particularly effective; performance depends on firm size, recency of information, market breadth and idiosyncratic risk. | Y35: Global cross-country evidence. | Z35: Gross focus [verify]. | AA35: Implementable combination. | AB35: International breadth | AC35: Out-of-US robustness [inference]. | AD35: 3 | AE35: Detailed core entry | AF35: Crossref match (title, author, year, journal)
A36: SPUR2026 | B36: Spurious Predictability in Financial Machine Learning | C36: [verify authors] | D36: 2026 | E36: Working paper (arXiv 2604.15531) | F36: WP | H36: Statistical inference | I36: No | J36: — | K36: — | L36: — | M36: — | N36: — | O36: — | P36: — | Q36: — | R36: — | S36: — | T36: — | U36: — | V36: — | W36: — | X36: Adaptive specification search produces statistically significant backtests under martingale-difference nulls; proposes a falsification audit with zero-predictability reference classes, microstructure placebos and a multiplicity-adjusted inflation gap. | Y36: — | Z36: — | AA36: — | AB36: — | AC36: — | AD36: 5 | AE36: Adopted as our credibility layer; raises the bar that competing submissions must clear. | AF36: Working paper (journal DOI not available/verified)
A37: FRLUX2025 | B37: FR-LUX: Friction-Aware, Regime-Conditioned Policy Optimization for Implementable Portfolio Management | C37: Zhang, J. | D37: 2025 | E37: Working paper (arXiv 2510.02986) | F37: WP | H37: Factor timing & regimes | I37: No | J37: — | K37: — | L37: — | M37: — | N37: — | O37: — | P37: — | Q37: — | R37: — | S37: — | T37: — | U37: — | V37: — | W37: — | X37: Reinforcement-learning policy with proportional and impact costs inside the reward, inaction bands, conditioning on four volatility-liquidity regimes; evaluated on a regime x cost grid with bootstrap CIs and multiple-testing corrections; reports a flatter cost-performance slope than baselines. | Y37: — | Z37: — | AA37: — | AB37: — | AC37: — | AD37: 5 | AE37: Closest new prior art for the conditioning x cost interaction (gap G2); cite and differentiate (single method vs factorial attribution; small asset space vs ~150-signal cross-section). | AF37: Working paper (journal DOI not available/verified)
A38: AHM2019 | B38: A Backtesting Protocol in the Era of Machine Learning | C38: Arnott, R.; Harvey, C.R.; Markowitz, H. | D38: 2019 | E38: Journal of Financial Data Science 1(1):64-74 | F38: T3 Practitioner | G38: https://doi.org/10.3905/jfds.2019.1.064 | H38: Statistical inference | I38: No | J38: — | K38: — | L38: — | M38: — | N38: — | O38: — | P38: — | Q38: — | R38: — | S38: — | T38: — | U38: — | V38: — | W38: — | X38: Checklist-style protocol for credible ML backtests. | Y38: — | Z38: — | AA38: — | AB38: — | AC38: — | AD38: 5 | AE38: Basis for reviewer-proof checklist. | AF38: Crossref match (title, author, year, journal)
A39: BBLZ2017 | B39: The Probability of Backtest Overfitting | C39: Bailey, D.H.; Borwein, J.; Lopez de Prado, M.; Zhu, Q.J. | D39: 2017 | E39: Journal of Computational Finance 20(4):39-69 | F39: T2 Quant/Field | G39: https://doi.org/10.21314/JCF.2016.322 | H39: Statistical inference | I39: No | J39: — | K39: — | L39: — | M39: — | N39: — | O39: — | P39: — | Q39: — | R39: — | S39: — | T39: — | U39: — | V39: — | W39: — | X39: CSCV estimates the probability that the in-sample best configuration underperforms out of sample. | Y39: — | Z39: — | AA39: — | AB39: — | AC39: — | AD39: 5 | AE39: PBO reporting. | AF39: DOI from publisher page/search; Crossref-confirmed
A40: HLZ2016 | B40: ... and the Cross-Section of Expected Returns | C40: Harvey, C.R.; Liu, Y.; Zhu, H. | D40: 2016 | E40: Review of Financial Studies 29(1):5-68 | F40: T1 General Finance | G40: https://doi.org/10.1093/rfs/hhv059 | H40: Replication & multiple testing | I40: No | J40: — | K40: — | L40: — | M40: — | N40: — | O40: — | P40: — | Q40: — | R40: — | S40: — | T40: — | U40: — | V40: — | W40: — | X40: Multiple-testing framework for 300+ factors; new factors should clear t > 3.0. | Y40: — | Z40: — | AA40: — | AB40: — | AC40: — | AD40: 5 | AE40: Significance hurdles. | AF40: DOI from publisher page/search; Crossref-confirmed
A41: LW2008 | B41: Robust Performance Hypothesis Testing with the Sharpe Ratio | C41: Ledoit, O.; Wolf, M. | D41: 2008 | E41: Journal of Empirical Finance 15(5):850-859 | F41: T2 Quant/Field | G41: https://doi.org/10.1016/j.jempfin.2008.03.002 | H41: Statistical inference | I41: No | J41: — | K41: — | L41: — | M41: — | N41: — | O41: — | P41: — | Q41: — | R41: — | S41: — | T41: — | U41: — | V41: — | W41: — | X41: HAC and studentised circular block bootstrap tests for Sharpe-ratio differences. | Y41: — | Z41: — | AA41: — | AB41: — | AC41: — | AD41: 5 | AE41: Primary Sharpe-difference test. | AF41: Crossref match (title, author, year, journal)
A42: HAN2005 | B42: A Test for Superior Predictive Ability | C42: Hansen, P.R. | D42: 2005 | E42: Journal of Business & Economic Statistics 23(4):365-380 | F42: T2 Quant/Field | G42: https://doi.org/10.1198/073500105000000063 | H42: Statistical inference | I42: No | J42: — | K42: — | L42: — | M42: — | N42: — | O42: — | P42: — | Q42: — | R42: — | S42: — | T42: — | U42: — | V42: — | W42: — | X42: SPA test: more powerful and less sensitive to poor alternatives than the Reality Check. | Y42: — | Z42: — | AA42: — | AB42: — | AC42: — | AD42: 5 | AE42: Primary data-snooping test. | AF42: DOI from publisher page/search; Crossref-confirmed
A43: WHI2000 | B43: A Reality Check for Data Snooping | C43: White, H. | D43: 2000 | E43: Econometrica 68(5):1097-1126 | F43: Econometrics general | G43: https://doi.org/10.1111/1468-0262.00152 | H43: Statistical inference | I43: No | J43: — | K43: — | L43: — | M43: — | N43: — | O43: — | P43: — | Q43: — | R43: — | S43: — | T43: — | U43: — | V43: — | W43: — | X43: Bootstrap test that the best of many models does not beat a benchmark. | Y43: — | Z43: — | AA43: — | AB43: — | AC43: — | AD43: 5 | AE43: Data-snooping control. | AF43: DOI from publisher page/search; Crossref-confirmed
A44: CW2026 | B44: What Useful Alphas? | C44: Chen, A.Y.; Welch, I. | D44: 2026 | E44: Working paper (arXiv 2607.06502) | F44: WP | H44: TC & implementability | I44: No | J44: — | K44: — | L44: — | M44: — | N44: — | O44: — | P44: — | Q44: — | R44: — | S44: — | T44: — | U44: — | V44: — | W44: — | X44: About 200 published anomalies: median return 48 bp/month through 2005 falls to 19 bp post-2005 and to about 7 bp after liquidity/microcap restrictions; modest cost allowances eliminate it. | Y44: — | Z44: — | AA44: — | AB44: — | AC44: — | AD44: 4 | AE44: Sets a sobering prior: net signal-level alpha is near zero recently. | AF44: Working paper (journal DOI not available/verified)
A45: SPO2026 | B45: Decision-Induced Ranking Explains Prediction Inflation and Excessive Turnover in SPO-Based Portfolio Optimization | C45: Wang, Y.; Hasuike, T. | D45: 2026 | E45: Working paper (arXiv 2605.01176) | F45: WP | H45: End-to-end / decision-focused | I45: No | J45: — | K45: — | L45: — | M45: — | N45: — | O45: — | P45: — | Q45: — | R45: — | S45: — | T45: — | U45: — | V45: — | W45: — | X45: Shows decision-focused (SPO) portfolio learning inflates return signals and churns the book; proposes clipping, min-max rescaling and partial portfolio adjustment. | Y45: — | Z45: — | AA45: — | AB45: — | AC45: — | AD45: 4 | AE45: Our economic-objective cells adopt these controls and report inflation as a diagnostic. | AF45: Working paper (journal DOI not available/verified)
A46: VSC2026 | B46: The Virtue of Sparsity in Complexity | C46: Afsharhajari, N.; Li, J.Y.-M. | D46: 2026 | E46: Working paper (arXiv 2604.17166) | F46: WP | H46: ML asset pricing | I46: No | J46: — | K46: — | L46: — | M46: — | N46: — | O46: — | P46: — | Q46: — | R46: — | S46: — | T46: — | U46: — | V46: — | W46: — | X46: Distinguishes capacity sparsity from factor sparsity; with nonlinear feature expansions, basis-pursuit sparse selection keeps improving in the high-complexity regime while the dense ridgeless benchmark plateaus. | Y46: — | Z46: — | AA46: — | AB46: — | AC46: — | AD46: 4 | AE46: Motivates the dense/sparse arms of our complexity ladder (levels A2/A3). | AF46: Working paper (journal DOI not available/verified)
A47: BLLP2025 | B47: Missing Financial Data | C47: Bryzgalova, S.; Lerner, S.; Lettau, M.; Pelger, M. | D47: 2025 | E47: Review of Financial Studies 38(3):803-882 | F47: T1 General Finance | G47: https://doi.org/10.1093/rfs/hhae036 | H47: Data & measurement | I47: No | J47: — | K47: — | L47: — | M47: — | N47: — | O47: — | P47: — | Q47: — | R47: — | S47: — | T47: — | U47: — | V47: — | W47: — | X47: Characteristics are frequently missing, not at random; proposes cross-sectional and time-series imputation. [verify pages] | Y47: — | Z47: — | AA47: — | AB47: — | AC47: — | AD47: 4 | AE47: Missing-data handling protocol. | AF47: Crossref match (title, author, year, journal)
A48: FHNW2025 | B48: Missing Data in Asset Pricing Panels | C48: Freyberger, J.; Hoppner, B.; Neuhierl, A.; Weber, M. | D48: 2025 | E48: Review of Financial Studies 38(3):760-802 | F48: T1 General Finance | G48: https://doi.org/10.1093/rfs/hhae003 | H48: Data & measurement | I48: No | J48: — | K48: — | L48: — | M48: — | N48: — | O48: — | P48: — | Q48: — | R48: — | S48: — | T48: — | U48: — | V48: — | W48: — | X48: Generalised method of moments approach to missing characteristics; imputation choices affect results. [verify pages] | Y48: — | Z48: — | AA48: — | AB48: — | AC48: — | AD48: 4 | AE48: Missing-data handling protocol. | AF48: Crossref match (title, author, year, journal)
A49: AGK2024 | B49: Efficient Estimation of Bid-Ask Spreads from Open, High, Low, and Close Prices | C49: Ardia, D.; Guidotti, E.; Kroencke, T.A. | D49: 2024 | E49: Journal of Financial Economics 161:103916 | F49: T1 General Finance | G49: https://doi.org/10.1016/j.jfineco.2024.103916 | H49: TC & implementability | I49: No | J49: — | K49: — | L49: — | M49: — | N49: — | O49: — | P49: — | Q49: — | R49: — | S49: — | T49: — | U49: — | V49: — | W49: — | X49: EDGE estimator from OHLC prices; R package 'bidask'. | Y49: — | Z49: — | AA49: — | AB49: — | AC49: — | AD49: 4 | AE49: Preferred low-frequency spread estimator where TAQ unavailable. [verify volume] | AF49: Crossref match (title, author, year, journal)
A50: CPPS2024 | B50: Conformal Predictive Portfolio Selection | C50: Kato, M. | D50: 2024 | E50: Working paper (arXiv 2410.16333, revised 2025) | F50: WP | H50: Portfolio construction | I50: No | J50: — | K50: — | L50: — | M50: — | N50: — | O50: — | P50: — | Q50: — | R50: — | S50: — | T50: — | U50: — | V50: — | W50: — | X50: Combines conformal prediction intervals with portfolio selection across AR, random-forest and neural-network forecasters. | Y50: — | Z50: — | AA50: — | AB50: — | AC50: — | AD50: 4 | AE50: Basis for uncertainty level D2 (calibrated intervals) instead of raw ensemble dispersion. | AF50: Working paper (journal DOI not available/verified)
A51: MENK2024 | B51: Nonstandard Errors | C51: Menkveld, A.J.; et al. | D51: 2024 | E51: Journal of Finance 79(3):2339-2390 | F51: T1 General Finance | H51: Replication & multiple testing | I51: No | J51: — | K51: — | L51: — | M51: — | N51: — | O51: — | P51: — | Q51: — | R51: — | S51: — | T51: — | U51: — | V51: — | W51: — | X51: 164 teams testing the same hypotheses on the same data produce dispersion (non-standard errors) comparable to standard errors. | Y51: — | Z51: — | AA51: — | AB51: — | AC51: — | AD51: 4 | AE51: Justifies multiverse reporting. | AF51: No DOI verified
A52: BK2023 | B52: Integrating Prediction in Mean-Variance Portfolio Optimization | C52: Butler, A.; Kwon, R.H. | D52: 2023 | E52: Quantitative Finance 23(3):429-452 | F52: T2 Quant/Field | G52: https://doi.org/10.1080/14697688.2022.2162432 | H52: End-to-end / decision-focused | I52: No | J52: — | K52: — | L52: — | M52: — | N52: — | O52: — | P52: — | Q52: — | R52: — | S52: — | T52: — | U52: — | V52: — | W52: — | X52: Integrated prediction-optimisation (IPO) with closed forms for unconstrained MVO and differentiable QP layers otherwise; lower realised cost than predict-then-optimize. | Y52: — | Z52: — | AA52: — | AB52: — | AC52: — | AD52: 4 | AE52: Decision-focused MVO benchmark. | AF52: DOI from publisher page/search; Crossref-confirmed
A53: KX2023 | B53: Financial Machine Learning | C53: Kelly, B.; Xiu, D. | D53: 2023 | E53: Foundations and Trends in Finance 13(3-4):205-363 | F53: Survey | G53: https://doi.org/10.1561/500000064 | H53: ML asset pricing | I53: No | J53: — | K53: — | L53: — | M53: — | N53: — | O53: — | P53: — | Q53: — | R53: — | S53: — | T53: — | U53: — | V53: — | W53: — | X53: Survey of ML in financial markets for economists and machine learners. | Y53: — | Z53: — | AA53: — | AB53: — | AC53: — | AD53: 4 | AE53: Background survey. | AF53: Crossref match (title, author, year, journal)
A54: EG2022 | B54: Smart 'Predict, then Optimize' | C54: Elmachtoub, A.N.; Grigas, P. | D54: 2022 | E54: Management Science 68(1):9-26 | F54: T1b Finance/OR | G54: https://doi.org/10.1287/mnsc.2020.3922 | H54: End-to-end / decision-focused | I54: No | J54: — | K54: — | L54: — | M54: — | N54: — | O54: — | P54: — | Q54: — | R54: — | S54: — | T54: — | U54: — | V54: — | W54: — | X54: SPO+ loss trains predictors on decision regret rather than prediction error. | Y54: — | Z54: — | AA54: — | AB54: — | AC54: — | AD54: 4 | AE54: Decision-focused loss foundation. | AF54: Crossref match (title, author, year, journal)
A55: CTWZ2021 | B55: AlphaPortfolio: Direct Construction through Deep Reinforcement Learning and Interpretable AI | C55: Cong, L.W.; Tang, K.; Wang, J.; Zhang, Y. | D55: 2021 | E55: Working paper (SSRN 3554486; NBER w35195) | F55: WP | H55: End-to-end / decision-focused | I55: No | J55: — | K55: — | L55: — | M55: — | N55: — | O55: — | P55: — | Q55: — | R55: — | S55: — | T55: — | U55: — | V55: — | W55: — | X55: Transformer-based RL directly optimises investor objectives; out-of-sample Sharpe above 2 and 13%+ alpha with monthly rebalancing in US equities, robust to excluding small/illiquid stocks; 'economic distillation' for interpretation. | Y55: — | Z55: — | AA55: — | AB55: — | AC55: — | AD55: 4 | AE55: Direct-construction benchmark; implementability claims need independent replication [inference]. | AF55: Working paper (journal DOI not available/verified)
A56: FNW2020 | B56: Dissecting Characteristics Nonparametrically | C56: Freyberger, J.; Neuhierl, A.; Weber, M. | D56: 2020 | E56: Review of Financial Studies 33(5):2326-2377 | F56: T1 General Finance | G56: https://doi.org/10.1093/rfs/hhz123 | H56: ML asset pricing | I56: No | J56: — | K56: — | L56: — | M56: — | N56: — | O56: — | P56: — | Q56: — | R56: — | S56: — | T56: — | U56: — | V56: — | W56: — | X56: Adaptive group LASSO selects characteristics with incremental information and estimates nonlinear effects; many predictors add nothing incremental; nonlinearity matters. | Y56: — | Z56: — | AA56: — | AB56: — | AC56: — | AD56: 4 | AE56: Evidence on redundancy; nonparametric-selection benchmark. | AF56: DOI from publisher page/search; Crossref-confirmed
A57: HXZ2020 | B57: Replicating Anomalies | C57: Hou, K.; Xue, C.; Zhang, L. | D57: 2020 | E57: Review of Financial Studies 33(5):2019-2133 | F57: T1 General Finance | G57: https://doi.org/10.1093/rfs/hhy131 | H57: Replication & multiple testing | I57: No | J57: — | K57: — | L57: — | M57: — | N57: — | O57: — | P57: — | Q57: — | R57: — | S57: — | T57: — | U57: — | V57: — | W57: — | X57: 65% of 452 anomalies fail |t| > 1.96 and 82% fail 2.78 with NYSE breakpoints and value weighting; replicated magnitudes are smaller. | Y57: — | Z57: — | AA57: — | AB57: — | AC57: — | AD57: 4 | AE57: Microcap and weighting discipline. | AF57: DOI from publisher page/search; Crossref-confirmed
A58: KNS2020 | B58: Shrinking the Cross-Section | C58: Kozak, S.; Nagel, S.; Santosh, S. | D58: 2020 | E58: Journal of Financial Economics 135(2):271-292 | F58: T1 General Finance | G58: https://doi.org/10.1016/j.jfineco.2019.06.008 | H58: ML asset pricing | I58: No | J58: — | K58: — | L58: — | M58: — | N58: — | O58: — | P58: — | Q58: — | R58: — | S58: — | T58: — | U58: — | V58: — | W58: — | X58: Robust SDF from many predictors via an economically motivated prior that shrinks low-variance principal components. | Y58: — | Z58: — | AA58: — | AB58: — | AC58: — | AD58: 4 | AE58: Mean-variance signal-combination benchmark with shrinkage. | AF58: Crossref match (title, author, year, journal)
A59: RJ2019 | B59: Machine Learning for Stock Selection | C59: Rasekhschaffe, K.C.; Jones, R.C. | D59: 2019 | E59: Financial Analysts Journal 75(3):70-88 | F59: T3 Practitioner | G59: https://doi.org/10.1080/0015198X.2019.1596678 | H59: ML strategies & implementability | I59: No | J59: — | K59: — | L59: — | M59: — | N59: — | O59: — | P59: — | Q59: — | R59: — | S59: — | T59: — | U59: — | V59: — | W59: — | X59: Practitioner framework: forecast combination across algorithms and feature engineering to limit overfitting in cross-sectional stock selection. | Y59: — | Z59: — | AA59: — | AB59: — | AC59: — | AD59: 4 | AE59: Practitioner combination baseline. | AF59: DOI from publisher page/search; Crossref-confirmed
A60: LDP2018 | B60: Advances in Financial Machine Learning | C60: Lopez de Prado, M. | D60: 2018 | E60: Wiley (book) | F60: Book | H60: Statistical inference | I60: No | J60: — | K60: — | L60: — | M60: — | N60: — | O60: — | P60: — | Q60: — | R60: — | S60: — | T60: — | U60: — | V60: — | W60: — | X60: Purged k-fold cross-validation with embargo, meta-labelling, backtest overfitting. | Y60: — | Z60: — | AA60: — | AB60: — | AC60: — | AD60: 4 | AE60: Validation protocol for overlapping labels. | AF60: Book (no DOI recorded)
A61: HAR2017 | B61: Presidential Address: The Scientific Outlook in Financial Economics | C61: Harvey, C.R. | D61: 2017 | E61: Journal of Finance 72(4):1399-1440 | F61: T1 General Finance | G61: https://doi.org/10.1111/jofi.12530 | H61: Replication & multiple testing | I61: No | J61: — | K61: — | L61: — | M61: — | N61: — | O61: — | P61: — | Q61: — | R61: — | S61: — | T61: — | U61: — | V61: — | W61: — | X61: Incentives produce p-hacking; recommends Bayesian-style minimum Bayes factors and higher standards. | Y61: — | Z61: — | AA61: — | AB61: — | AC61: — | AD61: 4 | AE61: Reviewer expectations on integrity. | AF61: Crossref match (title, author, year, journal)
A62: LL2017 | B62: A Unified Approach to Interpreting Model Predictions | C62: Lundberg, S.M.; Lee, S.-I. | D62: 2017 | E62: Advances in Neural Information Processing Systems 30 | F62: ML venue | H62: ML methods | I62: No | J62: — | K62: — | L62: — | M62: — | N62: — | O62: — | P62: — | Q62: — | R62: — | S62: — | T62: — | U62: — | V62: — | W62: — | X62: SHAP values unify additive feature attribution methods. | Y62: — | Z62: — | AA62: — | AB62: — | AC62: — | AD62: 4 | AE62: Signal attribution. | AF62: Conference/ML venue (not in Crossref or not matched)
A63: LPB2017 | B63: Simple and Scalable Predictive Uncertainty Estimation Using Deep Ensembles | C63: Lakshminarayanan, B.; Pritzel, A.; Blundell, C. | D63: 2017 | E63: Advances in Neural Information Processing Systems 30 | F63: ML venue | H63: ML methods | I63: No | J63: — | K63: — | L63: — | M63: — | N63: — | O63: — | P63: — | Q63: — | R63: — | S63: — | T63: — | U63: — | V63: — | W63: — | X63: Deep ensembles give calibrated predictive uncertainty. | Y63: — | Z63: — | AA63: — | AB63: — | AC63: — | AD63: 4 | AE63: Uncertainty estimator. | AF63: Conference/ML venue (not in Crossref or not matched)
A64: LW2017 | B64: Nonlinear Shrinkage of the Covariance Matrix for Portfolio Selection: Markowitz Meets Goldilocks | C64: Ledoit, O.; Wolf, M. | D64: 2017 | E64: Review of Financial Studies 30(12):4349-4388 | F64: T1 General Finance | G64: https://doi.org/10.1093/rfs/hhx052 | H64: Portfolio construction | I64: No | J64: — | K64: — | L64: — | M64: — | N64: — | O64: — | P64: — | Q64: — | R64: — | S64: — | T64: — | U64: — | V64: — | W64: — | X64: Nonlinear shrinkage covariance estimator improves large-dimensional portfolio selection. | Y64: — | Z64: — | AA64: — | AB64: — | AC64: — | AD64: 4 | AE64: Default covariance estimator. | AF64: DOI from publisher page/search; Crossref-confirmed
A65: DM2016 | B65: Momentum Crashes | C65: Daniel, K.; Moskowitz, T.J. | D65: 2016 | E65: Journal of Financial Economics 122(2):221-247 | F65: T1 General Finance | G65: https://doi.org/10.1016/j.jfineco.2015.12.002 | H65: Factor timing & regimes | I65: No | J65: — | K65: — | L65: — | M65: — | N65: — | O65: — | P65: — | Q65: — | R65: — | S65: — | T65: — | U65: — | V65: — | W65: — | X65: Momentum crashes in panic states after market declines when volatility is high; dynamic momentum doubles Sharpe. | Y65: — | Z65: — | AA65: — | AB65: — | AC65: — | AD65: 4 | AE65: Economic prior: state-dependent momentum weight. | AF65: Crossref match (title, author, year, journal)
A66: HL2015 | B66: Backtesting | C66: Harvey, C.R.; Liu, Y. | D66: 2015 | E66: Journal of Portfolio Management 42(1):13-28 | F66: T3 Practitioner | G66: https://doi.org/10.3905/jpm.2015.42.1.013 | H66: Statistical inference | I66: No | J66: — | K66: — | L66: — | M66: — | N66: — | O66: — | P66: — | Q66: — | R66: — | S66: — | T66: — | U66: — | V66: — | W66: — | X66: Sharpe-ratio haircuts for multiple testing. | Y66: — | Z66: — | AA66: — | AB66: — | AC66: — | AD66: 4 | AE66: Haircut Sharpe reporting. | AF66: Crossref match (title, author, year, journal)
A67: CSS2012 | B67: Factor Alignment Problems and Quantitative Portfolio Management | C67: Ceria, S.; Saxena, A.; Stubbs, R.A. | D67: 2012 | E67: Journal of Portfolio Management 38(2):29-43 | F67: T3 Practitioner | G67: https://doi.org/10.3905/jpm.2012.2012.1.021 | H67: Portfolio construction | I67: No | J67: — | K67: — | L67: — | M67: — | N67: — | O67: — | P67: — | Q67: — | R67: — | S67: — | T67: — | U67: — | V67: — | W67: — | X67: Misalignment between alpha model, risk model and constraints creates unintended exposures and risk underestimation. | Y67: — | Z67: — | AA67: — | AB67: — | AC67: — | AD67: 4 | AE67: Alignment diagnostics for ML alpha. | AF67: Crossref match (title, author, year, journal)
A68: SYY2012 | B68: The Short of It: Investor Sentiment and Anomalies | C68: Stambaugh, R.F.; Yu, J.; Yuan, Y. | D68: 2012 | E68: Journal of Financial Economics 104(2):288-302 | F68: T1 General Finance | G68: https://doi.org/10.1016/j.jfineco.2011.12.001 | H68: Factor timing & regimes | I68: No | J68: — | K68: — | L68: — | M68: — | N68: — | O68: — | P68: — | Q68: — | R68: — | S68: — | T68: — | U68: — | V68: — | W68: — | X68: Anomalies are stronger following high sentiment, mostly on the short leg. | Y68: — | Z68: — | AA68: — | AB68: — | AC68: — | AD68: 4 | AE68: Economic prior for state dependence. | AF68: Crossref match (title, author, year, journal)
A69: HLN2011 | B69: The Model Confidence Set | C69: Hansen, P.R.; Lunde, A.; Nason, J.M. | D69: 2011 | E69: Econometrica 79(2):453-497 | F69: Econometrics general | G69: https://doi.org/10.3982/ecta5771 | H69: Statistical inference | I69: No | J69: — | K69: — | L69: — | M69: — | N69: — | O69: — | P69: — | Q69: — | R69: — | S69: — | T69: — | U69: — | V69: — | W69: — | X69: Set of models containing the best with given confidence. | Y69: — | Z69: — | AA69: — | AB69: — | AC69: — | AD69: 4 | AE69: Report the MCS of design cells. | AF69: Crossref match (online/issue year differs)
A70: DGU2009 | B70: Optimal Versus Naive Diversification: How Inefficient Is the 1/N Portfolio Strategy? | C70: DeMiguel, V.; Garlappi, L.; Uppal, R. | D70: 2009 | E70: Review of Financial Studies 22(5):1915-1953 | F70: T1 General Finance | G70: https://doi.org/10.1093/rfs/hhm075 | H70: Portfolio construction | I70: No | J70: — | K70: — | L70: — | M70: — | N70: — | O70: — | P70: — | Q70: — | R70: — | S70: — | T70: — | U70: — | V70: — | W70: — | X70: None of 14 optimisation models consistently beats 1/N out of sample in Sharpe, CEQ or turnover. | Y70: — | Z70: — | AA70: — | AB70: — | AC70: — | AD70: 4 | AE70: Naive benchmark is mandatory. | AF70: DOI from publisher page/search
A71: HAS2009 | B71: Trading Costs and Returns for U.S. Equities: Estimating Effective Costs from Daily Data | C71: Hasbrouck, J. | D71: 2009 | E71: Journal of Finance 64(3):1445-1477 | F71: T1 General Finance | G71: https://doi.org/10.1111/j.1540-6261.2009.01469.x | H71: TC & implementability | I71: No | J71: — | K71: — | L71: — | M71: — | N71: — | O71: — | P71: — | Q71: — | R71: — | S71: — | T71: — | U71: — | V71: — | W71: — | X71: Gibbs-sampler estimate of effective costs from daily prices, validated against TAQ. | Y71: — | Z71: — | AA71: — | AB71: — | AC71: — | AD71: 4 | AE71: Historical spread estimator. | AF71: DOI from publisher page/search; Crossref-confirmed
A72: CW2007 | B72: Approximately Normal Tests for Equal Predictive Accuracy in Nested Models | C72: Clark, T.E.; West, K.D. | D72: 2007 | E72: Journal of Econometrics 138(1):291-311 | F72: T2 Quant/Field | G72: https://doi.org/10.1016/j.jeconom.2006.05.023 | H72: Statistical inference | I72: No | J72: — | K72: — | L72: — | M72: — | N72: — | O72: — | P72: — | Q72: — | R72: — | S72: — | T72: — | U72: — | V72: — | W72: — | X72: Adjusted MSPE test for nested models. | Y72: — | Z72: — | AA72: — | AB72: — | AC72: — | AD72: 4 | AE72: Nested model comparisons (static vs conditional). | AF72: Crossref match (title, author, year, journal)
A73: RW2005 | B73: Stepwise Multiple Testing as Formalized Data Snooping | C73: Romano, J.P.; Wolf, M. | D73: 2005 | E73: Econometrica 73(4):1237-1282 | F73: Econometrics general | G73: https://doi.org/10.1111/j.1468-0262.2005.00615.x | H73: Statistical inference | I73: No | J73: — | K73: — | L73: — | M73: — | N73: — | O73: — | P73: — | Q73: — | R73: — | S73: — | T73: — | U73: — | V73: — | W73: — | X73: StepM identifies which models beat the benchmark with FWER control. | Y73: — | Z73: — | AA73: — | AB73: — | AC73: — | AD73: 4 | AE73: Which cells beat the benchmark. | AF73: Crossref match (title, author, year, journal)
A74: CST2002 | B74: Portfolio Constraints and the Fundamental Law of Active Management | C74: Clarke, R.; de Silva, H.; Thorley, S. | D74: 2002 | E74: Financial Analysts Journal 58(5):48-66 | F74: T3 Practitioner | G74: https://doi.org/10.2469/faj.v58.n5.2468 | H74: Portfolio construction | I74: No | J74: — | K74: — | L74: — | M74: — | N74: — | O74: — | P74: — | Q74: — | R74: — | S74: — | T74: — | U74: — | V74: — | W74: — | X74: Introduces the transfer coefficient: constraints limit how much forecast information reaches portfolio weights. | Y74: — | Z74: — | AA74: — | AB74: — | AC74: — | AD74: 4 | AE74: Transfer-coefficient reporting in our metrics. | AF74: Crossref match (title, author, year, journal)
A75: LO2002 | B75: The Statistics of Sharpe Ratios | C75: Lo, A.W. | D75: 2002 | E75: Financial Analysts Journal 58(4):36-52 | F75: T3 Practitioner | G75: https://doi.org/10.2469/faj.v58.n4.2453 | H75: Statistical inference | I75: No | J75: — | K75: — | L75: — | M75: — | N75: — | O75: — | P75: — | Q75: — | R75: — | S75: — | T75: — | U75: — | V75: — | W75: — | X75: Sampling distribution of Sharpe ratios under serial correlation; annualisation errors. | Y75: — | Z75: — | AA75: — | AB75: — | AC75: — | AD75: 4 | AE75: Sharpe inference. | AF75: Crossref match (title, author, year, journal)
A76: GK2000 | B76: Active Portfolio Management (2nd ed.) | C76: Grinold, R.C.; Kahn, R.N. | D76: 2000 | E76: McGraw-Hill (book) | F76: Book | H76: Portfolio construction | I76: No | J76: — | K76: — | L76: — | M76: — | N76: — | O76: — | P76: — | Q76: — | R76: — | S76: — | T76: — | U76: — | V76: — | W76: — | X76: Alpha forecasting, signal combination and portfolio construction for quantitative managers. | Y76: — | Z76: — | AA76: — | AB76: — | AC76: — | AD76: 4 | AE76: Practitioner combination canon. | AF76: Book (no DOI recorded)
A77: SHU1997 | B77: The Delisting Bias in CRSP Data | C77: Shumway, T. | D77: 1997 | E77: Journal of Finance 52(1):327-340 | F77: T1 General Finance | G77: https://doi.org/10.1111/j.1540-6261.1997.tb03818.x | H77: Data & measurement | I77: No | J77: — | K77: — | L77: — | M77: — | N77: — | O77: — | P77: — | Q77: — | R77: — | S77: — | T77: — | U77: — | V77: — | W77: — | X77: Missing performance-related delisting returns bias CRSP returns upward. | Y77: — | Z77: — | AA77: — | AB77: — | AC77: — | AD77: 4 | AE77: Delisting-return correction. | AF77: Crossref match (title, author, year, journal)
A78: DM1995 | B78: Comparing Predictive Accuracy | C78: Diebold, F.X.; Mariano, R.S. | D78: 1995 | E78: Journal of Business & Economic Statistics 13(3):253-263 | F78: T2 Quant/Field | G78: https://doi.org/10.1080/07350015.1995.10524599 | H78: Statistical inference | I78: No | J78: — | K78: — | L78: — | M78: — | N78: — | O78: — | P78: — | Q78: — | R78: — | S78: — | T78: — | U78: — | V78: — | W78: — | X78: Test of equal predictive accuracy. | Y78: — | Z78: — | AA78: — | AB78: — | AC78: — | AD78: 4 | AE78: Forecast comparison. | AF78: Crossref match (title, author, year, journal)
A79: PR1994 | B79: The Stationary Bootstrap | C79: Politis, D.N.; Romano, J.P. | D79: 1994 | E79: Journal of the American Statistical Association 89(428):1303-1313 | F79: Econometrics general | G79: https://doi.org/10.1080/01621459.1994.10476870 | H79: Statistical inference | I79: No | J79: — | K79: — | L79: — | M79: — | N79: — | O79: — | P79: — | Q79: — | R79: — | S79: — | T79: — | U79: — | V79: — | W79: — | X79: Random-block bootstrap for stationary dependent data. | Y79: — | Z79: — | AA79: — | AB79: — | AC79: — | AD79: 4 | AE79: Bootstrap for SPA/RC. | AF79: Crossref match (title, author, year, journal)
A80: GRIN1989 | B80: The Fundamental Law of Active Management | C80: Grinold, R.C. | D80: 1989 | E80: Journal of Portfolio Management 15(3):30-37 | F80: T3 Practitioner | G80: https://doi.org/10.3905/jpm.1989.409211 | H80: Portfolio construction | I80: No | J80: — | K80: — | L80: — | M80: — | N80: — | O80: — | P80: — | Q80: — | R80: — | S80: — | T80: — | U80: — | V80: — | W80: — | X80: IR approximately IC x sqrt(breadth). | Y80: — | Z80: — | AA80: — | AB80: — | AC80: — | AD80: 4 | AE80: Links IC to IR; motivates IC-weighting baseline. | AF80: Crossref match (title, author, year, journal)
A81: NW1987 | B81: A Simple, Positive Semi-Definite, Heteroskedasticity and Autocorrelation Consistent Covariance Matrix | C81: Newey, W.K.; West, K.D. | D81: 1987 | E81: Econometrica 55(3):703-708 | F81: Econometrics general | G81: https://doi.org/10.2307/1913610 | H81: Statistical inference | I81: No | J81: — | K81: — | L81: — | M81: — | N81: — | O81: — | P81: — | Q81: — | R81: — | S81: — | T81: — | U81: — | V81: — | W81: — | X81: HAC standard errors. | Y81: — | Z81: — | AA81: — | AB81: — | AC81: — | AD81: 4 | AE81: Mean-return and alpha t-statistics. | AF81: Crossref match (title, author, year, journal)
A82: AIPT2025 | B82: APT or AIPT? The Surprising Dominance of Large Factor Models | C82: Kelly, B.; et al. | D82: 2025 | E82: Working paper (EDHEC-hosted PDF, Oct 2025) [verify authors and venue] | F82: WP | H82: ML asset pricing | I82: No | J82: — | K82: — | L82: — | M82: — | N82: — | O82: — | P82: — | Q82: — | R82: — | S82: — | T82: — | U82: — | V82: — | W82: — | X82: Whether extra factors help depends on the eigenvalue distribution: concentrated spectra show no virtue of complexity, diffuse ones do. | Y82: — | Z82: — | AA82: — | AB82: — | AC82: — | AD82: 3 | AE82: Basis for our spectrum diagnostic, which predicts when the complexity rung should pay. | AF82: Working paper (journal DOI not available/verified)
A83: BPZ2025 | B83: Forest through the Trees: Building Cross-Sections of Stock Returns | C83: Bryzgalova, S.; Pelger, M.; Zhu, J. | D83: 2025 | E83: Journal of Finance 80:2447-2506 | F83: T1 General Finance | G83: https://doi.org/10.1111/jofi.13477 | H83: ML asset pricing | I83: No | J83: — | K83: — | L83: — | M83: — | N83: — | O83: — | P83: — | Q83: — | R83: — | S83: — | T83: — | U83: — | V83: — | W83: — | X83: Decision trees (AP-Trees) build characteristic-managed test portfolios that span the SDF. | Y83: — | Z83: — | AA83: — | AB83: — | AC83: — | AD83: 3 | AE83: Interpretable nonlinear interaction structure. | AF83: DOI from publisher page/search; Crossref-confirmed
A84: CFHH2025 | B84: Growing the Efficient Frontier on Panel Trees | C84: Cong, L.W.; Feng, G.; He, J.; He, X. | D84: 2025 | E84: Journal of Financial Economics 167:104024 | F84: T1 General Finance | G84: https://doi.org/10.1016/j.jfineco.2025.104024 | H84: ML asset pricing | I84: No | J84: — | K84: — | L84: — | M84: — | N84: — | O84: — | P84: — | Q84: — | R84: — | S84: — | T84: — | U84: — | V84: — | W84: — | X84: P-Trees on unbalanced panels create test assets and traded factors that advance the efficient frontier. | Y84: — | Z84: — | AA84: — | AB84: — | AC84: — | AD84: 3 | AE84: Tree-based interaction discovery benchmark. | AF84: Crossref match (title, author, year, journal)
A85: FMYY2025 | B85: Cost-aware Portfolios in a Large Universe of Assets | C85: Fan, Q.; Medeiros, M.C.; Yang, H.; Yang, S. | D85: 2025 | E85: Working paper (arXiv 2412.11575, revised Aug 2025) | F85: WP | H85: Portfolio construction | I85: No | J85: — | K85: — | L85: — | M85: — | N85: — | O85: — | P85: — | Q85: — | R85: — | S85: — | T85: — | U85: — | V85: — | W85: — | X85: Mean-variance rebalancing with nonconvex penalties under proportional and quadratic transaction costs in high dimensions; S&P 500 and Russell 2000 evidence. | Y85: — | Z85: — | AA85: — | AB85: — | AC85: — | AD85: 3 | AE85: Alternative cost-aware optimiser to cite alongside ours. | AF85: Working paper (journal DOI not available/verified)
A86: KKMX2025 | B86: Artificial Intelligence Asset Pricing Models | C86: Kelly, B.; Kuznetsov, B.; Malamud, S.; Xu, T.A. | D86: 2025 | E86: Working paper (NBER w33351) | F86: WP | H86: ML asset pricing | I86: No | J86: — | K86: — | L86: — | M86: — | N86: — | O86: — | P86: — | Q86: — | R86: — | S86: — | T86: — | U86: — | V86: — | W86: — | X86: Transformer embedded in the SDF shares information across assets; large pricing-error reductions versus prior ML models. | Y86: — | Z86: — | AA86: — | AB86: — | AC86: — | AD86: 3 | AE86: Attention-based cross-asset combination; implementability untested [inference]. | AF86: Working paper (journal DOI not available/verified)
A87: LLG2025 | B87: Limits To (Machine) Learning | C87: Chen, Z.; Kelly, B.; Malamud, S. | D87: 2025 | E87: Working paper (arXiv 2512.12735) | F87: WP | H87: ML asset pricing | I87: No | J87: — | K87: — | L87: — | M87: — | N87: — | O87: — | P87: — | Q87: — | R87: — | S87: — | T87: — | U87: — | V87: — | W87: — | X87: Defines a limits-to-learning gap: a lower bound on the discrepancy between empirical fit and the population benchmark, implying standard ML understates true predictability. | Y87: — | Z87: — | AA87: — | AB87: — | AC87: — | AD87: 3 | AE87: Cited when interpreting small R2 and IC values. | AF87: Working paper (journal DOI not available/verified)
A88: SERT2025 | B88: Asset Pricing in Pre-trained Transformer | C88: Lai, S. | D88: 2025 | E88: Working paper (arXiv 2505.01575) | F88: WP | H88: ML asset pricing | I88: No | J88: — | K88: — | L88: — | M88: — | N88: — | O88: — | P88: — | Q88: — | R88: — | S88: — | T88: — | U88: — | V88: — | W88: — | X88: Transformer variants for US large-cap pricing across pre-pandemic, pandemic and post-pandemic periods; reports high out-of-sample R2 during turbulent markets. | Y88: — | Z88: — | AA88: — | AB88: — | AC88: — | AD88: 3 | AE88: Context for our cross-sectional attention rung (level A4); look-ahead handling is not documented in the abstract [verify]. | AF88: Working paper (journal DOI not available/verified)
A89: SYM2025 | B89: Dynamic Asset Allocation with Asset-Specific Regime Forecasts | C89: Shu, Y.; Yu, C.; Mulvey, J.M. | D89: 2025 | E89: Annals of Operations Research 346(1):285-318 | F89: T2 Quant/Field | G89: https://doi.org/10.1007/s10479-024-06266-0 | H89: Factor timing & regimes | I89: No | J89: — | K89: — | L89: — | M89: — | N89: — | O89: — | P89: — | Q89: — | R89: — | S89: — | T89: — | U89: — | V89: — | W89: — | X89: Statistical jump models label regimes; gradient-boosted classifiers forecast them; forecasts feed mean-variance allocation. | Y89: — | Z89: — | AA89: — | AB89: — | AC89: — | AD89: 3 | AE89: Regime-forecast module template. | AF89: Crossref match (title, author, year, journal)
A90: KNNV2024 | B90: Factor Timing with Portfolio Characteristics | C90: Kagkadis, A.; Nolte, I.; Nolte, S.; Vasilas, N. | D90: 2024 | E90: Review of Asset Pricing Studies 14(1):84-118 | F90: T1b Finance/OR | G90: https://doi.org/10.1093/rapstu/raad010 | H90: Factor timing & regimes | I90: No | J90: — | K90: — | L90: — | M90: — | N90: — | O90: — | P90: — | Q90: — | R90: — | S90: — | T90: — | U90: — | V90: — | W90: — | X90: Timing factor returns with their portfolios' characteristics outperforms existing timing methods. | Y90: — | Z90: — | AA90: — | AB90: — | AC90: — | AD90: 3 | AE90: Timing-predictor candidate. | AF90: Crossref match (title, author, year, journal)
A91: ULM2024 | B91: End-to-End Risk Budgeting Portfolio Optimization with Neural Networks | C91: Uysal, A.S.; Li, X.; Mulvey, J.M. | D91: 2024 | E91: Annals of Operations Research 339(1-2):397-426 | F91: T2 Quant/Field | G91: https://doi.org/10.1007/s10479-023-05539-4 | H91: End-to-end / decision-focused | I91: No | J91: — | K91: — | L91: — | M91: — | N91: — | O91: — | P91: — | Q91: — | R91: — | S91: — | T91: — | U91: — | V91: — | W91: — | X91: Model-based network with risk-budgeting implicit layer; ETF out-of-sample 2017-2021 Sharpe 1.16 vs 0.83 for pure risk budgeting. | Y91: — | Z91: — | AA91: — | AB91: — | AC91: — | AD91: 3 | AE91: Small-universe end-to-end evidence. | AF91: DOI from publisher page/search; Crossref-confirmed
A92: CI2023 | B92: Distributionally Robust End-to-End Portfolio Construction | C92: Costa, G.; Iyengar, G.N. | D92: 2023 | E92: Quantitative Finance 23(10):1465-1482 | F92: T2 Quant/Field | G92: https://doi.org/10.1080/14697688.2023.2236148 | H92: End-to-end / decision-focused | I92: No | J92: — | K92: — | L92: — | M92: — | N92: — | O92: — | P92: — | Q92: — | R92: — | S92: — | T92: — | U92: — | V92: — | W92: — | X92: End-to-end system with a DRO layer that learns robustness parameters. | Y92: — | Z92: — | AA92: — | AB92: — | AC92: — | AD92: 3 | AE92: Robust end-to-end benchmark. [verify pages] | AF92: DOI from publisher page/search; Crossref-confirmed
A93: DKKM2023 | B93: Complexity in Factor Pricing Models | C93: Didisheim, A.; Ke, S.; Kelly, B.; Malamud, S. | D93: 2023 | E93: Working paper (NBER w31689; SSRN 4574634) | F93: WP | H93: ML asset pricing | I93: No | J93: — | K93: — | L93: — | M93: — | N93: — | O93: — | P93: — | Q93: — | R93: — | S93: — | T93: — | U93: — | V93: — | W93: — | X93: Out-of-sample SDF Sharpe and pricing errors improve with model parameterisation; very large factor models outperform simpler ones. | Y93: — | Z93: — | AA93: — | AB93: — | AC93: — | AD93: 3 | AE93: Complexity dimension; must be confronted with costs. | AF93: Working paper (journal DOI not available/verified)
A94: DNMV2023 | B94: Model Comparison with Transaction Costs | C94: Detzel, A.; Novy-Marx, R.; Velikov, M. | D94: 2023 | E94: Journal of Finance 78(3):1743-1775 | F94: T1 General Finance | G94: https://doi.org/10.1111/jofi.13225 | H94: TC & implementability | I94: No | J94: — | K94: — | L94: — | M94: — | N94: — | O94: — | P94: — | Q94: — | R94: — | S94: — | T94: — | U94: — | V94: — | W94: — | X94: Ignoring costs biases model comparison toward high-cost factors; net of costs FF5 beats q-factor and six-factor models. | Y94: — | Z94: — | AA94: — | AB94: — | AC94: — | AD94: 3 | AE94: Net-of-cost alpha benchmark choice. | AF94: DOI from publisher page/search; Crossref-confirmed
A95: KMP2023 | B95: Principal Portfolios | C95: Kelly, B.; Malamud, S.; Pedersen, L.H. | D95: 2023 | E95: Journal of Finance 78(1):347-387 | F95: T1 General Finance | G95: https://doi.org/10.1111/jofi.13199 | H95: ML asset pricing | I95: No | J95: — | K95: — | L95: — | M95: — | N95: — | O95: — | P95: — | Q95: — | R95: — | S95: — | T95: — | U95: — | V95: — | W95: — | X95: When all signals predict all returns, optimal strategies are eigenvectors of the prediction matrix; principal portfolios earn out-of-sample alphas. | Y95: — | Z95: — | AA95: — | AB95: — | AC95: — | AD95: 3 | AE95: Cross-asset signal interactions. | AF95: DOI from publisher page/search; Crossref-confirmed
A96: BCZ2022 | B96: Distributionally Robust Mean-Variance Portfolio Selection with Wasserstein Distances | C96: Blanchet, J.; Chen, L.; Zhou, X.Y. | D96: 2022 | E96: Management Science 68(9):6382-6410 | F96: T1b Finance/OR | G96: https://doi.org/10.1287/mnsc.2021.4155 | H96: Portfolio construction | I96: No | J96: — | K96: — | L96: — | M96: — | N96: — | O96: — | P96: — | Q96: — | R96: — | S96: — | T96: — | U96: — | V96: — | W96: — | X96: Wasserstein DRO mean-variance with data-driven calibration of the ambiguity radius. | Y96: — | Z96: — | AA96: — | AB96: — | AC96: — | AD96: 3 | AE96: DRO optimiser variant. | AF96: Crossref match (title, author, year, journal)
A97: EL2022 | B97: Factor Momentum and the Momentum Factor | C97: Ehsani, S.; Linnainmaa, J.T. | D97: 2022 | E97: Journal of Finance 77(3):1877-1919 | F97: T1 General Finance | G97: https://doi.org/10.1111/jofi.13131 | H97: Factor timing & regimes | I97: No | J97: — | K97: — | L97: — | M97: — | N97: — | O97: — | P97: — | Q97: — | R97: — | S97: — | T97: — | U97: — | V97: — | W97: — | X97: Factors are autocorrelated (6 bp after losing years vs 51 bp after winning years); momentum times other factors. | Y97: — | Z97: — | AA97: — | AB97: — | AC97: — | AD97: 3 | AE97: Signal-level efficacy predictor. | AF97: DOI from publisher page/search; Crossref-confirmed
A98: GKX2022 | B98: Factor Models, Machine Learning, and Asset Pricing | C98: Giglio, S.; Kelly, B.; Xiu, D. | D98: 2022 | E98: Annual Review of Financial Economics 14:337-368 | F98: Survey | G98: https://doi.org/10.1146/annurev-financial-101521-104735 | H98: ML asset pricing | I98: No | J98: — | K98: — | L98: — | M98: — | N98: — | O98: — | P98: — | Q98: — | R98: — | S98: — | T98: — | U98: — | V98: — | W98: — | X98: Survey of factor models and ML methods in asset pricing. | Y98: — | Z98: — | AA98: — | AB98: — | AC98: — | AD98: 3 | AE98: Background survey. [verify pages] | AF98: Crossref match (title, author, year, journal)
A99: LWZ2022 | B99: Machine Learning in the Chinese Stock Market | C99: Leippold, M.; Wang, Q.; Zhou, W. | D99: 2022 | E99: Journal of Financial Economics 145(2):64-82 | F99: T1 General Finance | G99: https://doi.org/10.1016/j.jfineco.2021.08.017 | H99: ML asset pricing | I99: No | J99: — | K99: — | L99: — | M99: — | N99: — | O99: — | P99: — | Q99: — | R99: — | S99: — | T99: — | U99: — | V99: — | W99: — | X99: Liquidity is the most important predictor in China; retail presence drives short-term predictability; ML performance economically significant after costs. | Y99: — | Z99: — | AA99: — | AB99: — | AC99: — | AD99: 3 | AE99: Market-structure dependence of ML signals. | AF99: DOI from publisher page/search; Crossref-confirmed
A100: GKX2021 | B100: Autoencoder Asset Pricing Models | C100: Gu, S.; Kelly, B.; Xiu, D. | D100: 2021 | E100: Journal of Econometrics 222(1):429-450 | F100: T2 Quant/Field | G100: https://doi.org/10.1016/j.jeconom.2020.07.009 | H100: ML asset pricing | I100: No | J100: — | K100: — | L100: — | M100: — | N100: — | O100: — | P100: — | Q100: — | R100: — | S100: — | T100: — | U100: — | V100: — | W100: — | X100: Conditional autoencoder links characteristics to nonlinear conditional betas and latent factors under no-arbitrage. | Y100: — | Z100: — | AA100: — | AB100: — | AC100: — | AD100: 3 | AE100: Latent-factor benchmark; tested under restrictions by ACM2023. | AF100: Crossref match (title, author, year, journal)
A101: GLX2021 | B101: Thousands of Alpha Tests | C101: Giglio, S.; Liao, Y.; Xiu, D. | D101: 2021 | E101: Review of Financial Studies 34(7):3456-3496 | F101: T1 General Finance | G101: https://doi.org/10.1093/rfs/hhaa111 | H101: Replication & multiple testing | I101: No | J101: — | K101: — | L101: — | M101: — | N101: — | O101: — | P101: — | Q101: — | R101: — | S101: — | T101: — | U101: — | V101: — | W101: — | X101: FDR control for thousands of alpha tests with omitted factors. | Y101: — | Z101: — | AA101: — | AB101: — | AC101: — | AD101: 3 | AE101: Multiple-testing correction for signal-level claims. | AF101: Crossref match (title, author, year, journal)
A102: LLMSS2021 | B102: The Promises and Pitfalls of Machine Learning for Predicting Stock Returns | C102: Leung, E.; Lohre, H.; Mischlich, D.; Shea, Y.; Stroh, M. | D102: 2021 | E102: Journal of Financial Data Science 3(2):21-50 | F102: T3 Practitioner | G102: https://doi.org/10.3905/jfds.2021.1.062 | H102: ML strategies & implementability | I102: No | J102: — | K102: — | L102: — | M102: — | N102: — | O102: — | P102: — | Q102: — | R102: — | S102: — | T102: — | U102: — | V102: — | W102: — | X102: Compares GBM with OLS on large/mid-cap regional universes; quantifies where ML adds value and its pitfalls. | Y102: — | Z102: — | AA102: — | AB102: — | AC102: — | AD102: 3 | AE102: Large-cap evidence on ML value. | AF102: Crossref match (title, author, year, journal)
A103: NAG2021 | B103: Machine Learning in Asset Pricing | C103: Nagel, S. | D103: 2021 | E103: Princeton University Press (book) | F103: Book | H103: ML asset pricing | I103: No | J103: — | K103: — | L103: — | M103: — | N103: — | O103: — | P103: — | Q103: — | R103: — | S103: — | T103: — | U103: — | V103: — | W103: — | X103: Monograph on ML methods in asset pricing and their economic restrictions. | Y103: — | Z103: — | AA103: — | AB103: — | AC103: — | AD103: 3 | AE103: Background monograph. | AF103: Book (no DOI recorded)
A104: AZ2020 | B104: Visualizing the Effects of Predictor Variables in Black Box Supervised Learning Models | C104: Apley, D.W.; Zhu, J. | D104: 2020 | E104: Journal of the Royal Statistical Society Series B 82(4):1059-1086 | F104: Econometrics general | G104: https://doi.org/10.1111/rssb.12377 | H104: ML methods | I104: No | J104: — | K104: — | L104: — | M104: — | N104: — | O104: — | P104: — | Q104: — | R104: — | S104: — | T104: — | U104: — | V104: — | W104: — | X104: Accumulated local effects plots robust to correlated predictors. | Y104: — | Z104: — | AA104: — | AB104: — | AC104: — | AD104: 3 | AE104: Preferred over PDP with correlated signals. | AF104: Crossref match (title, author, year, journal)
A105: COWY2020 | B105: On the Performance of Volatility-Managed Portfolios | C105: Cederburg, S.; O'Doherty, M.S.; Wang, F.; Yan, X.S. | D105: 2020 | E105: Journal of Financial Economics 138(1):95-117 | F105: T1 General Finance | G105: https://doi.org/10.1016/j.jfineco.2020.04.015 | H105: Factor timing & regimes | I105: No | J105: — | K105: — | L105: — | M105: — | N105: — | O105: — | P105: — | Q105: — | R105: — | S105: — | T105: — | U105: — | V105: — | W105: — | X105: Volatility-managed strategies generally fail to beat unmanaged versions in real-time out-of-sample tests. | Y105: — | Z105: — | AA105: — | AB105: — | AC105: — | AD105: 3 | AE105: Caution against in-sample conditioning gains. | AF105: Crossref match (title, author, year, journal)
A106: FGX2020 | B106: Taming the Factor Zoo: A Test of New Factors | C106: Feng, G.; Giglio, S.; Xiu, D. | D106: 2020 | E106: Journal of Finance 75(3):1327-1370 | F106: T1 General Finance | G106: https://doi.org/10.1111/jofi.12883 | H106: Replication & multiple testing | I106: No | J106: — | K106: — | L106: — | M106: — | N106: — | O106: — | P106: — | Q106: — | R106: — | S106: — | T106: — | U106: — | V106: — | W106: — | X106: Double-selection LASSO evaluates a new factor's marginal contribution given a high-dimensional set of existing factors. | Y106: — | Z106: — | AA106: — | AB106: — | AC106: — | AD106: 3 | AE106: Incremental-value testing for new signals. | AF106: Crossref match (title, author, year, journal)
A107: PW2020 | B107: What You See Is Not What You Get: The Costs of Trading Market Anomalies | C107: Patton, A.J.; Weller, B.M. | D107: 2020 | E107: Journal of Financial Economics 137(2):515-549 | F107: T1 General Finance | G107: https://doi.org/10.1016/j.jfineco.2020.02.012 | H107: TC & implementability | I107: No | J107: — | K107: — | L107: — | M107: — | N107: — | O107: — | P107: — | Q107: — | R107: — | S107: — | T107: — | U107: — | V107: — | W107: — | X107: Infers implementation costs of anomalies from real-world fund returns relative to paper portfolios [verify magnitudes]. | Y107: — | Z107: — | AA107: — | AB107: — | AC107: — | AD107: 3 | AE107: Cost-calibration cross-check. | AF107: Crossref match (title, author, year, journal)
A108: AAB2019 | B108: Differentiable Convex Optimization Layers | C108: Agrawal, A.; Amos, B.; Barratt, S.; Boyd, S.; Diamond, S.; Kolter, J.Z. | D108: 2019 | E108: Advances in Neural Information Processing Systems 32 | F108: ML venue | H108: End-to-end / decision-focused | I108: No | J108: — | K108: — | L108: — | M108: — | N108: — | O108: — | P108: — | Q108: — | R108: — | S108: — | T108: — | U108: — | V108: — | W108: — | X108: cvxpylayers: differentiate through disciplined convex programs. | Y108: — | Z108: — | AA108: — | AB108: — | AC108: — | AD108: 3 | AE108: Tooling for cost-aware differentiable optimiser. [DOI not in Crossref] | AF108: Conference/ML venue (not in Crossref or not matched)
A109: KPS2019 | B109: Characteristics Are Covariances: A Unified Model of Risk and Return | C109: Kelly, B.; Pruitt, S.; Su, Y. | D109: 2019 | E109: Journal of Financial Economics 134(3):501-524 | F109: T1 General Finance | G109: https://doi.org/10.1016/j.jfineco.2019.05.001 | H109: ML asset pricing | I109: No | J109: — | K109: — | L109: — | M109: — | N109: — | O109: — | P109: — | Q109: — | R109: — | S109: — | T109: — | U109: — | V109: — | W109: — | X109: IPCA: characteristics instrument time-varying loadings; separates risk compensation from an anomaly intercept. | Y109: — | Z109: — | AA109: — | AB109: — | AC109: — | AD109: 3 | AE109: Risk-based benchmark and risk-model candidate. | AF109: DOI from publisher page/search; Crossref-confirmed
A110: NMV2019 | B110: Comparing Cost-Mitigation Techniques | C110: Novy-Marx, R.; Velikov, M. | D110: 2019 | E110: Financial Analysts Journal 75(1):85-102 | F110: T3 Practitioner | G110: https://doi.org/10.1080/0015198x.2018.1547057 | H110: TC & implementability | I110: No | J110: — | K110: — | L110: — | M110: — | N110: — | O110: — | P110: — | Q110: — | R110: — | S110: — | T110: — | U110: — | V110: — | W110: — | X110: Compares banding, staggering, and other cost-mitigation methods. | Y110: — | Z110: — | AA110: — | AB110: — | AC110: — | AD110: 3 | AE110: Heuristic mitigation benchmarks. | AF110: Crossref match (title, author, year, journal)
A111: NML2018 | B111: Dynamic Portfolio Optimization across Hidden Market Regimes | C111: Nystrup, P.; Madsen, H.; Lindstrom, E. | D111: 2018 | E111: Quantitative Finance 18(1):83-95 | F111: T2 Quant/Field | G111: https://doi.org/10.1080/14697688.2017.1342857 | H111: Factor timing & regimes | I111: No | J111: — | K111: — | L111: — | M111: — | N111: — | O111: — | P111: — | Q111: — | R111: — | S111: — | T111: — | U111: — | V111: — | W111: — | X111: HMM regime inference combined with model predictive control improves dynamic allocation. | Y111: — | Z111: — | AA111: — | AB111: — | AC111: — | AD111: 3 | AE111: Regime + MPC template. [verify details] | AF111: Crossref match (title, author, year, journal)
A112: AK2017 | B112: OptNet: Differentiable Optimization as a Layer in Neural Networks | C112: Amos, B.; Kolter, J.Z. | D112: 2017 | E112: Proceedings of ICML 2017 (PMLR 70) | F112: ML venue | H112: End-to-end / decision-focused | I112: No | J112: — | K112: — | L112: — | M112: — | N112: — | O112: — | P112: — | Q112: — | R112: — | S112: — | T112: — | U112: — | V112: — | W112: — | X112: Differentiable quadratic-programming layers. | Y112: — | Z112: — | AA112: — | AB112: — | AC112: — | AD112: 3 | AE112: Implementation of differentiable optimiser. [DOI not in Crossref] | AF112: Conference/ML venue (not in Crossref or not matched)
A113: AR2017 | B113: A Simple Estimation of Bid-Ask Spreads from Daily Close, High, and Low Prices | C113: Abdi, F.; Ranaldo, A. | D113: 2017 | E113: Review of Financial Studies 30(12):4437-4480 | F113: T1 General Finance | G113: https://doi.org/10.1093/rfs/hhx084 | H113: TC & implementability | I113: No | J113: — | K113: — | L113: — | M113: — | N113: — | O113: — | P113: — | Q113: — | R113: — | S113: — | T113: — | U113: — | V113: — | W113: — | X113: Close-high-low estimator with high correlation to TAQ effective spreads. | Y113: — | Z113: — | AA113: — | AB113: — | AC113: — | AD113: 3 | AE113: Low-frequency spread estimator. | AF113: Crossref match (title, author, year, journal)
A114: DAK2017 | B114: Task-based End-to-end Model Learning in Stochastic Optimization | C114: Donti, P.L.; Amos, B.; Kolter, J.Z. | D114: 2017 | E114: Advances in Neural Information Processing Systems 30 | F114: ML venue | H114: End-to-end / decision-focused | I114: No | J114: — | K114: — | L114: — | M114: — | N114: — | O114: — | P114: — | Q114: — | R114: — | S114: — | T114: — | U114: — | V114: — | W114: — | X114: Learn probabilistic models by differentiating through the downstream optimisation task. | Y114: — | Z114: — | AA114: — | AB114: — | AC114: — | AD114: 3 | AE114: End-to-end foundation. [DOI not in Crossref] | AF114: Conference/ML venue (not in Crossref or not matched)
A115: GHZ2017 | B115: The Characteristics that Provide Independent Information about Average U.S. Monthly Stock Returns | C115: Green, J.; Hand, J.R.M.; Zhang, X.F. | D115: 2017 | E115: Review of Financial Studies 30(12):4389-4436 | F115: T1 General Finance | G115: https://doi.org/10.1093/rfs/hhx019 | H115: Replication & multiple testing | I115: No | J115: — | K115: — | L115: — | M115: — | N115: — | O115: — | P115: — | Q115: — | R115: — | S115: — | T115: — | U115: — | V115: — | W115: — | X115: Few characteristics provide independent information in multivariate FM regressions, and fewer after 2003. | Y115: — | Z115: — | AA115: — | AB115: — | AC115: — | AD115: 3 | AE115: Redundancy and post-2003 decay evidence. | AF115: Crossref match (title, author, year, journal)
A116: KE2017 | B116: LightGBM: A Highly Efficient Gradient Boosting Decision Tree | C116: Ke, G.; et al. | D116: 2017 | E116: Advances in Neural Information Processing Systems 30 | F116: ML venue | H116: ML methods | I116: No | J116: — | K116: — | L116: — | M116: — | N116: — | O116: — | P116: — | Q116: — | R116: — | S116: — | T116: — | U116: — | V116: — | W116: — | X116: Histogram-based efficient GBDT. | Y116: — | Z116: — | AA116: — | AB116: — | AC116: — | AD116: 3 | AE116: Primary GBDT implementation. | AF116: Conference/ML venue (not in Crossref or not matched)
A117: LMR2017 | B117: Aggregation of Information About the Cross Section of Stock Returns: A Latent Variable Approach | C117: Light, N.; Maslov, D.; Rytchkov, O. | D117: 2017 | E117: Review of Financial Studies 30(4):1339-1381 | F117: T1 General Finance | G117: https://doi.org/10.1093/rfs/hhw102 | H117: ML asset pricing | I117: No | J117: — | K117: — | L117: — | M117: — | N117: — | O117: — | P117: — | Q117: — | R117: — | S117: — | T117: — | U117: — | V117: — | W117: — | X117: Latent-variable (PLS-type) aggregation of many characteristics into expected-return estimates. | Y117: — | Z117: — | AA117: — | AB117: — | AC117: — | AD117: 3 | AE117: Linear aggregation benchmark. | AF117: Crossref match (title, author, year, journal)
A118: MM2017 | B118: Volatility-Managed Portfolios | C118: Moreira, A.; Muir, T. | D118: 2017 | E118: Journal of Finance 72(4):1611-1644 | F118: T1 General Finance | G118: https://doi.org/10.1111/jofi.12513 | H118: Factor timing & regimes | I118: No | J118: — | K118: — | L118: — | M118: — | N118: — | O118: — | P118: — | Q118: — | R118: — | S118: — | T118: — | U118: — | V118: — | W118: — | X118: Scaling factors by inverse variance increases Sharpe ratios and alphas. | Y118: — | Z118: — | AA118: — | AB118: — | AC118: — | AD118: 3 | AE118: Conditioning benchmark. | AF118: Crossref match (title, author, year, journal)
A119: CG2016 | B119: XGBoost: A Scalable Tree Boosting System | C119: Chen, T.; Guestrin, C. | D119: 2016 | E119: Proceedings of ACM SIGKDD 2016 | F119: ML venue | H119: ML methods | I119: No | J119: — | K119: — | L119: — | M119: — | N119: — | O119: — | P119: — | Q119: — | R119: — | S119: — | T119: — | U119: — | V119: — | W119: — | X119: Scalable regularised gradient boosting. | Y119: — | Z119: — | AA119: — | AB119: — | AC119: — | AD119: 3 | AE119: GBDT implementation. | AF119: Conference/ML venue (not in Crossref or not matched)
A120: GG2016 | B120: Dropout as a Bayesian Approximation: Representing Model Uncertainty in Deep Learning | C120: Gal, Y.; Ghahramani, Z. | D120: 2016 | E120: Proceedings of ICML 2016 (PMLR 48) | F120: ML venue | H120: ML methods | I120: No | J120: — | K120: — | L120: — | M120: — | N120: — | O120: — | P120: — | Q120: — | R120: — | S120: — | T120: — | U120: — | V120: — | W120: — | X120: MC dropout approximates Bayesian uncertainty. | Y120: — | Z120: — | AA120: — | AB120: — | AC120: — | AD120: 3 | AE120: Uncertainty estimator alternative. | AF120: Conference/ML venue (not in Crossref or not matched)
A121: KYO2016 | B121: Market Microstructure Invariance: Empirical Hypotheses | C121: Kyle, A.S.; Obizhaeva, A.A. | D121: 2016 | E121: Econometrica 84(4):1345-1404 | F121: Econometrics general | G121: https://doi.org/10.3982/ecta10486 | H121: TC & implementability | I121: No | J121: — | K121: — | L121: — | M121: — | N121: — | O121: — | P121: — | Q121: — | R121: — | S121: — | T121: — | U121: — | V121: — | W121: — | X121: Invariance hypotheses imply scaling laws for bet sizes and transaction costs. | Y121: — | Z121: — | AA121: — | AB121: — | AC121: — | AD121: 3 | AE121: Market-impact functional form. | AF121: Crossref match (title, author, year, journal)
...

Sheet Summary
A1: Literature database summary (live formulas)
A2: All counts recompute from the Literature sheet; filter there to explore.
A4: Total entries | B4: =COUNTA(Literature!A:A)-1
A5: Core (detailed) entries | B5: =COUNTIF(Literature!I:I,"Yes")
A6: Entries with DOI link | B6: =COUNTIF(Literature!G:G,"https://doi.org/*")
A7: DOIs confirmed/matched via Crossref | B7: =COUNTIF(Literature!AF:AF,"*Crossref match*")+COUNTIF(Literature!AF:AF,"*Crossref-confirmed*")
A8: Published 2019 or later | B8: =COUNTIF(Literature!D:D,">=2019")
A9: Relevance 5 entries | B9: =COUNTIF(Literature!AD:AD,5)
A12: Strand | B12: Entries | C12: Core entries | D12: Avg relevance
A13: Data & measurement | B13: =COUNTIF(Literature!$H:$H,$A13) | C13: =COUNTIFS(Literature!$H:$H,$A13,Literature!$I:$I,"Yes") | D13: =IFERROR(ROUND(AVERAGEIF(Literature!$H:$H,$A13,Literature!$AD:$AD),2),"")
A14: End-to-end / decision-focused | B14: =COUNTIF(Literature!$H:$H,$A14) | C14: =COUNTIFS(Literature!$H:$H,$A14,Literature!$I:$I,"Yes") | D14: =IFERROR(ROUND(AVERAGEIF(Literature!$H:$H,$A14,Literature!$AD:$AD),2),"")
A15: Factor timing & regimes | B15: =COUNTIF(Literature!$H:$H,$A15) | C15: =COUNTIFS(Literature!$H:$H,$A15,Literature!$I:$I,"Yes") | D15: =IFERROR(ROUND(AVERAGEIF(Literature!$H:$H,$A15,Literature!$AD:$AD),2),"")
A16: Industry | B16: =COUNTIF(Literature!$H:$H,$A16) | C16: =COUNTIFS(Literature!$H:$H,$A16,Literature!$I:$I,"Yes") | D16: =IFERROR(ROUND(AVERAGEIF(Literature!$H:$H,$A16,Literature!$AD:$AD),2),"")
A17: ML asset pricing | B17: =COUNTIF(Literature!$H:$H,$A17) | C17: =COUNTIFS(Literature!$H:$H,$A17,Literature!$I:$I,"Yes") | D17: =IFERROR(ROUND(AVERAGEIF(Literature!$H:$H,$A17,Literature!$AD:$AD),2),"")
A18: ML methods | B18: =COUNTIF(Literature!$H:$H,$A18) | C18: =COUNTIFS(Literature!$H:$H,$A18,Literature!$I:$I,"Yes") | D18: =IFERROR(ROUND(AVERAGEIF(Literature!$H:$H,$A18,Literature!$AD:$AD),2),"")
A19: ML strategies & implementability | B19: =COUNTIF(Literature!$H:$H,$A19) | C19: =COUNTIFS(Literature!$H:$H,$A19,Literature!$I:$I,"Yes") | D19: =IFERROR(ROUND(AVERAGEIF(Literature!$H:$H,$A19,Literature!$AD:$AD),2),"")
A20: Portfolio construction | B20: =COUNTIF(Literature!$H:$H,$A20) | C20: =COUNTIFS(Literature!$H:$H,$A20,Literature!$I:$I,"Yes") | D20: =IFERROR(ROUND(AVERAGEIF(Literature!$H:$H,$A20,Literature!$AD:$AD),2),"")
A21: Replication & multiple testing | B21: =COUNTIF(Literature!$H:$H,$A21) | C21: =COUNTIFS(Literature!$H:$H,$A21,Literature!$I:$I,"Yes") | D21: =IFERROR(ROUND(AVERAGEIF(Literature!$H:$H,$A21,Literature!$AD:$AD),2),"")
A22: Statistical inference | B22: =COUNTIF(Literature!$H:$H,$A22) | C22: =COUNTIFS(Literature!$H:$H,$A22,Literature!$I:$I,"Yes") | D22: =IFERROR(ROUND(AVERAGEIF(Literature!$H:$H,$A22,Literature!$AD:$AD),2),"")
A23: TC & implementability | B23: =COUNTIF(Literature!$H:$H,$A23) | C23: =COUNTIFS(Literature!$H:$H,$A23,Literature!$I:$I,"Yes") | D23: =IFERROR(ROUND(AVERAGEIF(Literature!$H:$H,$A23,Literature!$AD:$AD),2),"")
A26: Journal tier | B26: Entries
A27: Book | B27: =COUNTIF(Literature!$F:$F,$A27)
A28: Econometrics general | B28: =COUNTIF(Literature!$F:$F,$A28)
A29: Industry | B29: =COUNTIF(Literature!$F:$F,$A29)
A30: ML venue | B30: =COUNTIF(Literature!$F:$F,$A30)
A31: Survey | B31: =COUNTIF(Literature!$F:$F,$A31)
A32: T1 General Finance | B32: =COUNTIF(Literature!$F:$F,$A32)
A33: T1b Finance/OR | B33: =COUNTIF(Literature!$F:$F,$A33)
A34: T2 Quant/Field | B34: =COUNTIF(Literature!$F:$F,$A34)
A35: T3 Practitioner | B35: =COUNTIF(Literature!$F:$F,$A35)
A36: WP | B36: =COUNTIF(Literature!$F:$F,$A36)
A39: Period | B39: From | C39: To | D39: Entries
A40: <2000 | B40: 1900 | C40: 1999 | D40: =COUNTIFS(Literature!$D:$D,">="&B40,Literature!$D:$D,"<="&C40)
A41: 2000-2009 | B41: 2000 | C41: 2009 | D41: =COUNTIFS(Literature!$D:$D,">="&B41,Literature!$D:$D,"<="&C41)
A42: 2010-2014 | B42: 2010 | C42: 2014 | D42: =COUNTIFS(Literature!$D:$D,">="&B42,Literature!$D:$D,"<="&C42)
A43: 2015-2019 | B43: 2015 | C43: 2019 | D43: =COUNTIFS(Literature!$D:$D,">="&B43,Literature!$D:$D,"<="&C43)
A44: 2020-2022 | B44: 2020 | C44: 2022 | D44: =COUNTIFS(Literature!$D:$D,">="&B44,Literature!$D:$D,"<="&C44)
A45: 2023-2026 | B45: 2023 | C45: 2026 | D45: =COUNTIFS(Literature!$D:$D,">="&B45,Literature!$D:$D,"<="&C45)

Sheet Closest_Prior_Art
A1: # | B1: Paper | C1: Status | D1: What it does | E1: Overlap with our claim | F1: Differentiation | G1: Threat level | H1: Last checked
A2: 1 | B2: JKMP2026 | C2: RFS 2026 | D2: ML + trading-cost-aware learning of weights; implementable frontier; economic feature importance | E2: Objective dimension (iii); static nonlinear economic-loss learner | F2: We nest it as a cell; add conditioning, uncertainty, interactions, mechanism tests | G2: High | H2: Sep 2026
A3: 2 | B3: SWZ2023 | C3: MS 2026 (Crossref) | D3: Deep parametric portfolio policies; robust to costs | E3: Nonlinear economic-objective cell | F3: Factorial attribution; state dependence; formal snooping control | G3: High | H3: Sep 2026
A4: 3 | B4: DMNU2020 | C4: RFS 2020 | D4: Linear PPP with TC; netting | E4: Linear economic-loss cell | F4: Nonlinear and conditional cells; netting attribution | G4: Medium | H4: Sep 2026
A5: 4 | B5: DMU2024 | C5: JF 2024 | D5: Conditional multifactor (volatility) net of costs | E5: Conditioning x costs in low dimension | F5: Stock-level high-dimensional conditioning; many states; mechanism tests | G5: High (for G2) | H5: Sep 2026
A6: 5 | B6: ACM2023 | C6: MS 2023 | D6: ML under economic restrictions | E6: Motivation | F6: We propose/attribute, not only diagnose | G6: Low | H6: Sep 2026
A7: 6 | B7: CHK2024 | C7: SSRN WP | D7: 1,056 ML designs; non-standard errors | E7: Design-grid methodology | F7: Our factors are economic ingredients evaluated net of costs with a common optimiser | G7: Medium | H7: Sep 2026
A8: 7 | B8: LAL2025 | C8: EFM 2025 | D8: 5,376 portfolios; design choices incl. portfolio construction | E8: Design-grid methodology | F8: Same as above | G8: Medium | H8: Sep 2026
A9: 8 | B9: NRRZ2024 | C9: SSRN WP | D9: Factor-zoo timing | E9: State-variable predictability | F9: Stock-level implementation with costs | G9: Medium | H9: Sep 2026
A10: 9 | B10: LMNS2025 | C10: arXiv WP | D10: NN forecast uncertainty; uncertainty-averse portfolios | E10: Uncertainty dimension (iv) | F10: Interaction with costs and conditioning | G10: Medium-High (for iv) | H10: Sep 2026
A11: 10 | B11: AHV2023 | C11: SSRN WP | D11: ML strategies net of costs and decay | E11: Net-of-cost evaluation | F11: Cost-aware learning, attribution | G11: Medium | H11: Sep 2026
A12: 11 | B12: BHHH2023 | C12: JFDS 2023 | D12: Horizon choice and ML alpha net | E12: Horizon/turnover lever | F12: Horizon is a robustness factor | G12: Low-Medium | H12: Sep 2026
... A25: 24 | B25: FMYY2025 | C25: arXiv WP (Dec 2024, rev. 2025) | D25: Cost-aware mean-variance with nonconvex penalties in large universes; S&P 500 and Russell 2000 | E25: Our optimiser stage | F25: Optimisation methodology, not attribution; we can cite it as an alternative cost-aware optimiser | G25: Low-Medium | H25: Sep 2026

Sheet Legend
A1: Evidence conventions
A2: Applies to every text field in the Literature sheet
A4: Plain statement | B4: Verified from abstract, publisher page, authors' repository or search summary of those sources
A5: [inference] | B5: Research team's reading or synthesis; not a claim by the authors
A6: [verify] | B6: Could not be confirmed from an accessible primary source; check full text before citing
A7: Relevance 1-5 | B7: Team judgement of relevance to the selected research design
A8: DOI Verification Status | B8: How the DOI was obtained; see 08_References/crossref_verification.csv
