Workbook

Sheet Experiments
A1: Experiment ID | B1: Phase | C1: Block | D1: Experiment | E1: Hypothesis | F1: Model | G1: Dataset | H1: Benchmark | I1: Metrics | J1: Statistical Test | K1: Expected Outcome (pre-registered hypothesis, not a result) | L1: Priority | M1: Status | N1: Owner | O1: Planned Start (month) | P1: Planned End (month) | Q1: Evidence Location | R1: Notes
A2: E00 | B2: 2 | C2: Data integrity | D2: Point-in-time panel audit | E2: Panel has no look-ahead: accounting data lagged by availability date; delisting returns applied. | F2: n/a | G2: CRSP/Compustat monthly 1963-2025 | H2: CRSP value-weighted index; Ken French factors | I2: Correlation of rebuilt FF factors with Ken French series; missing-share by year | J2: Correlation > 0.95 threshold | K2: Rebuilt factors match library closely | L2: Must | M2: Not started | O2: 2 | P2: 4
A3: E01 | B3: 3 | C3: Signal library | D3: Signal replication vs original papers | E3: Rebuilt signals reproduce published long-short t-stats. | F3: Univariate sorts | G3: Signal panel (JKP/OpenAP definitions) | H3: Chen-Zimmermann reproduced t-stats | I3: Slope/R2 of our t-stats on theirs | J3: Regression; share with t>1.96 | K3: Slope near CZ2022's 0.88; R2 high | L3: Must | M3: Not started | O3: 3 | P3: 5
A4: E02 | B4: 3 | C4: Signal library | D4: Signal quality and decay profile | E4: Signals differ in IC decay speed and turnover; fast signals are costlier. | F4: Univariate IC by horizon 1-12m | G4: Signal panel | H4: n/a | I4: Mean IC, ICIR, IC half-life, signal autocorrelation, implied turnover | J4: Newey-West t on IC | K4: Wide heterogeneity; price-based signals decay fastest | L4: Must | M4: Not started | O4: 3 | P4: 5
A5: E03 | B5: 3 | C5: Signal library | D5: Redundancy and clustering | E5: Signals cluster into ~13 themes; within-theme redundancy is high. | F5: Hierarchical clustering on rank correlations of signals and of signal returns | G5: Signal panel | H5: JKP 13 themes | I5: Cluster purity, effective number of signals | J5: Bootstrap cluster stability | K5: Clusters broadly align with JKP themes | L5: Should | M5: Not started | O5: 3 | P5: 5
A6: E10 | B6: 4 | C6: Baselines | D6: Naive combinations | E6: Equal-weight z-score, theme-EW, IC-weighted, ICIR-weighted and inverse-vol combinations are strong net-of-cost baselines. | F6: Rule-based | G6: Main universe | H6: Each other | I6: IC, gross/net Sharpe, turnover | J6: Ledoit-Wolf Sharpe difference | K6: Simple combos have low turnover and competitive net Sharpe | L6: Must | M6: Not started | O6: 5 | P6: 6
A7: E11 | B7: 4 | C7: Baselines | D7: Linear statistical combinations | E7: Fama-MacBeth (Lewellen), ridge, elastic net, PLS improve IC over naive. | F7: FM rolling slopes; ridge; ENet; PLS | G7: Main universe | H7: E10 best | I7: OOS R2, IC, net Sharpe | J7: Clark-West; DM | K7: Modest IC gain; net gain uncertain | L7: Must | M7: Not started | O7: 5 | P7: 6
A8: E12 | B8: 4 | C8: Baselines | D8: Mean-variance signal-portfolio combination | E8: KNS-style shrunk SDF over signal portfolios is a strong linear benchmark. | F8: KNS2020 L2-shrinkage SDF | G8: Signal long-short portfolios | H8: E10/E11 | I8: Net Sharpe | J8: LW2008 test | K8: Competitive gross, higher turnover | L8: Must | M8: Not started | O8: 5 | P8: 6
A9: E13 | B9: 4 | C9: Baselines | D9: Published ML benchmarks | E9: GKX-style NN/GBDT and JKMP Portfolio-ML replicate approximately. | F9: GKX NN3; LightGBM; JKMP Portfolio-ML code | G9: Main universe | H9: Published numbers | I9: IC, OOS R2, net Sharpe | J9: Tracking vs published | K9: Directionally consistent replication | L9: Must | M9: Not started | O9: 5 | P9: 6
A10: E14 | B10: 4 | C10: Baselines | D10: Linear cost-aware PPP | E10: DMNU-style linear PPP with costs is a strong implementable benchmark. | F10: Linear PPP with TC | G10: Main universe | H10: E10-E13 | I10: Net utility, net Sharpe | J10: LW2008; SPA | K10: Beats cost-agnostic linear models net | L10: Must | M10: Not started | O10: 5 | P10: 6
A11: E20 | B11: 5 | C11: Factorial core | D11: Cell LS-P: Linear, Static, Prediction loss | E11: Reference cell. | F11: Ridge | G11: Main universe | H11: - | I11: All core metrics | J11: - | K11: Reference | L11: Must | M11: Not started | O11: 6 | P11: 9
A12: E21 | B12: 5 | C12: Factorial core | D12: Cell NS-P: Nonlinear, Static, Prediction loss | E12: H1: nonlinearity raises gross IC/Sharpe vs LS-P. | F12: LightGBM + NN ensemble | G12: Main universe | H12: E20 | I12: Gross and net deltas | J12: Clark-West; LW2008; SPA | K12: Gross gain; net gain at least 50% smaller | L12: Must | M12: Not started | O12: 6 | P12: 9
A13: E22 | B13: 5 | C13: Factorial core | D13: Cell LC-P: Linear, Conditional, Prediction loss | E13: H2a: conditioning adds little net value under prediction loss. | F13: Ridge with signal x state interactions | G13: Main universe | H13: E20 | I13: Net delta; turnover | J13: SPA; Clark-West | K13: Small/insignificant net gain | L13: Must | M13: Not started | O13: 6 | P13: 9
... A41: E64 | B41: 7 | C41: Interpretation | D41: Alpha-risk alignment diagnostics | E41: Nonlinear alphas show larger ex-post risk underestimation. | F41: All cells | G41: Main universe | H41: CSS2012 | I41: Bias statistic | J41: - | K41: Larger bias for nonlinear cells | L41: Could | M41: Not started | O41: 9 | P41: 11

Sheet Summary
A1: Experiment progress (live formulas)
A2: Change Status in the Experiments sheet; this sheet updates automatically
A4: Block | B4: Not started | C4: In progress | D4: Blocked | E4: Done | F4: Dropped | G4: Total | H4: % Done
A5: Data integrity | B5: =COUNTIFS(Experiments!$C:$C,$A5,Experiments!$M:$M,B$4) | C5: =COUNTIFS(Experiments!$C:$C,$A5,Experiments!$M:$M,C$4) | D5: =COUNTIFS(Experiments!$C:$C,$A5,Experiments!$M:$M,D$4) | E5: =COUNTIFS(Experiments!$C:$C,$A5,Experiments!$M:$M,E$4) | F5: =COUNTIFS(Experiments!$C:$C,$A5,Experiments!$M:$M,F$4) | G5: =COUNTIF(Experiments!$C:$C,$A5) | H5: =IFERROR(E5/G5,0)
A6: Signal library | B6: =COUNTIFS(Experiments!$C:$C,$A6,Experiments!$M:$M,B$4) | C6: =COUNTIFS(Experiments!$C:$C,$A6,Experiments!$M:$M,C$4) | D6: =COUNTIFS(Experiments!$C:$C,$A6,Experiments!$M:$M,D$4) | E6: =COUNTIFS(Experiments!$C:$C,$A6,Experiments!$M:$M,E$4) | F6: =COUNTIFS(Experiments!$C:$C,$A6,Experiments!$M:$M,F$4) | G6: =COUNTIF(Experiments!$C:$C,$A6) | H6: =IFERROR(E6/G6,0)
A7: Baselines | B7: =COUNTIFS(Experiments!$C:$C,$A7,Experiments!$M:$M,B$4) | C7: =COUNTIFS(Experiments!$C:$C,$A7,Experiments!$M:$M,C$4) | D7: =COUNTIFS(Experiments!$C:$C,$A7,Experiments!$M:$M,D$4) | E7: =COUNTIFS(Experiments!$C:$C,$A7,Experiments!$M:$M,E$4) | F7: =COUNTIFS(Experiments!$C:$C,$A7,Experiments!$M:$M,F$4) | G7: =COUNTIF(Experiments!$C:$C,$A7) | H7: =IFERROR(E7/G7,0)
A8: Factorial core | B8: =COUNTIFS(Experiments!$C:$C,$A8,Experiments!$M:$M,B$4) | C8: =COUNTIFS(Experiments!$C:$C,$A8,Experiments!$M:$M,C$4) | D8: =COUNTIFS(Experiments!$C:$C,$A8,Experiments!$M:$M,D$4) | E8: =COUNTIFS(Experiments!$C:$C,$A8,Experiments!$M:$M,E$4) | F8: =COUNTIFS(Experiments!$C:$C,$A8,Experiments!$M:$M,F$4) | G8: =COUNTIF(Experiments!$C:$C,$A8) | H8: =IFERROR(E8/G8,0)
A9: Portfolio & costs | B9: =COUNTIFS(Experiments!$C:$C,$A9,Experiments!$M:$M,B$4) | C9: =COUNTIFS(Experiments!$C:$C,$A9,Experiments!$M:$M,C$4) | D9: =COUNTIFS(Experiments!$C:$C,$A9,Experiments!$M:$M,D$4) | E9: =COUNTIFS(Experiments!$C:$C,$A9,Experiments!$M:$M,E$4) | F9: =COUNTIFS(Experiments!$C:$C,$A9,Experiments!$M:$M,F$4) | G9: =COUNTIF(Experiments!$C:$C,$A9) | H9: =IFERROR(E9/G9,0)
A10: Inference | B10: =COUNTIFS(Experiments!$C:$C,$A10,Experiments!$M:$M,B$4) | C10: =COUNTIFS(Experiments!$C:$C,$A10,Experiments!$M:$M,C$4) | D10: =COUNTIFS(Experiments!$C:$C,$A10,Experiments!$M:$M,D$4) | E10: =COUNTIFS(Experiments!$C:$C,$A10,Experiments!$M:$M,E$4) | F10: =COUNTIFS(Experiments!$C:$C,$A10,Experiments!$M:$M,F$4) | G10: =COUNTIF(Experiments!$C:$C,$A10) | H10: =IFERROR(E10/G10,0)
A11: Robustness | B11: =COUNTIFS(Experiments!$C:$C,$A11,Experiments!$M:$M,B$4) | C11: =COUNTIFS(Experiments!$C:$C,$A11,Experiments!$M:$M,C$4) | D11: =COUNTIFS(Experiments!$C:$C,$A11,Experiments!$M:$M,D$4) | E11: =COUNTIFS(Experiments!$C:$C,$A11,Experiments!$M:$M,E$4) | F11: =COUNTIFS(Experiments!$C:$C,$A11,Experiments!$M:$M,F$4) | G11: =COUNTIF(Experiments!$C:$C,$A11) | H11: =IFERROR(E11/G11,0)
A12: Interpretation | B12: =COUNTIFS(Experiments!$C:$C,$A12,Experiments!$M:$M,B$4) | C12: =COUNTIFS(Experiments!$C:$C,$A12,Experiments!$M:$M,C$4) | D12: =COUNTIFS(Experiments!$C:$C,$A12,Experiments!$M:$M,D$4) | E12: =COUNTIFS(Experiments!$C:$C,$A12,Experiments!$M:$M,E$4) | F12: =COUNTIFS(Experiments!$C:$C,$A12,Experiments!$M:$M,F$4) | G12: =COUNTIF(Experiments!$C:$C,$A12) | H12: =IFERROR(E12/G12,0)
A13: All experiments | B13: =SUM(B5:B12) | C13: =SUM(C5:C12) | D13: =SUM(D5:D12) | E13: =SUM(E5:E12) | F13: =SUM(F5:F12) | G13: =SUM(G5:G12) | H13: =IFERROR(E13/G13,0)
A16: Priority | B16: Count | C16: Done
A17: Must | B17: =COUNTIF(Experiments!$L:$L,$A17) | C17: =COUNTIFS(Experiments!$L:$L,$A17,Experiments!$M:$M,"Done")
A18: Should | B18: =COUNTIF(Experiments!$L:$L,$A18) | C18: =COUNTIFS(Experiments!$L:$L,$A18,Experiments!$M:$M,"Done")
A19: Could | B19: =COUNTIF(Experiments!$L:$L,$A19) | C19: =COUNTIFS(Experiments!$L:$L,$A19,Experiments!$M:$M,"Done")

Sheet Factorial_Cells
A1: 16-cell factorial design with orthogonal contrast coding (formulas)
A2: Contrast columns (+1/-1) and interactions are formulas; use them to regress monthly net returns of cells on effects (E29)
A3: Cell | B3: Form | C3: Conditioning | D3: Objective | E3: Uncertainty | F3: Experiment | G3: x_Nonlinear | H3: x_State | I3: x_Economic | J3: x_Uncertainty | K3: State x Economic | L3: Nonlinear x Economic | M3: Nonlinear x State | N3: Uncertainty x Economic
A4: L-S-P-0 | B4: Linear | C4: Static | D4: Prediction | E4: None | F4: E20 | G4: =IF(B4="Nonlinear",1,-1) | H4: =IF(C4="State",1,-1) | I4: =IF(D4="Economic",1,-1) | J4: =IF(E4="None",-1,1) | K4: =H4*I4 | L4: =G4*I4 | M4: =G4*H4 | N4: =J4*I4
A5: L-S-P-U | B5: Linear | C5: Static | D5: Prediction | E5: Ensemble shrinkage | F5: E20 + E28 | G5: =IF(B5="Nonlinear",1,-1) | H5: =IF(C5="State",1,-1) | I5: =IF(D5="Economic",1,-1) | J5: =IF(E5="None",-1,1) | K5: =H5*I5 | L5: =G5*I5 | M5: =G5*H5 | N5: =J5*I5
A6: L-S-E-0 | B6: Linear | C6: Static | D6: Economic | E6: None | F6: E24 | G6: =IF(B6="Nonlinear",1,-1) | H6: =IF(C6="State",1,-1) | I6: =IF(D6="Economic",1,-1) | J6: =IF(E6="None",-1,1) | K6: =H6*I6 | L6: =G6*I6 | M6: =G6*H6 | N6: =J6*I6
A7: L-S-E-U | B7: Linear | C7: Static | D7: Economic | E7: Ensemble shrinkage | F7: E24 + E28 | G7: =IF(B7="Nonlinear",1,-1) | H7: =IF(C7="State",1,-1) | I7: =IF(D7="Economic",1,-1) | J7: =IF(E7="None",-1,1) | K7: =H7*I7 | L7: =G7*I7 | M7: =G7*H7 | N7: =J7*I7
A8: L-C-P-0 | B8: Linear | C8: State | D8: Prediction | E8: None | F8: E22 | G8: =IF(B8="Nonlinear",1,-1) | H8: =IF(C8="State",1,-1) | I8: =IF(D8="Economic",1,-1) | J8: =IF(E8="None",-1,1) | K8: =H8*I8 | L8: =G8*I8 | M8: =G8*H8 | N8: =J8*I8
A9: L-C-P-U | B9: Linear | C9: State | D9: Prediction | E9: Ensemble shrinkage | F9: E22 + E28 | G9: =IF(B9="Nonlinear",1,-1) | H9: =IF(C9="State",1,-1) | I9: =IF(D9="Economic",1,-1) | J9: =IF(E9="None",-1,1) | K9: =H9*I9 | L9: =G9*I9 | M9: =G9*H9 | N9: =J9*I9
A10: L-C-E-0 | B10: Linear | C10: State | D10: Economic | E10: None | F10: E26 | G10: =IF(B10="Nonlinear",1,-1) | H10: =IF(C10="State",1,-1) | I10: =IF(D10="Economic",1,-1) | J10: =IF(E10="None",-1,1) | K10: =H10*I10 | L10: =G10*I10 | M10: =G10*H10 | N10: =J10*I10
A11: L-C-E-U | B11: Linear | C11: State | D11: Economic | E11: Ensemble shrinkage | F11: E26 + E28 | G11: =IF(B11="Nonlinear",1,-1) | H11: =IF(C11="State",1,-1) | I11: =IF(D11="Economic",1,-1) | J11: =IF(E11="None",-1,1) | K11: =H11*I11 | L11: =G11*I11 | M11: =G11*H11 | N11: =J11*I11
A12: N-S-P-0 | B12: Nonlinear | C12: Static | D12: Prediction | E12: None | F12: E21 | G12: =IF(B12="Nonlinear",1,-1) | H12: =IF(C12="State",1,-1) | I12: =IF(D12="Economic",1,-1) | J12: =IF(E12="None",-1,1) | K12: =H12*I12 | L12: =G12*I12 | M12: =G12*H12 | N12: =J12*I12
A13: N-S-P-U | B13: Nonlinear | C13: Static | D13: Prediction | E13: Ensemble shrinkage | F13: E21 + E28 | G13: =IF(B13="Nonlinear",1,-1) | H13: =IF(C13="State",1,-1) | I13: =IF(D13="Economic",1,-1) | J13: =IF(E13="None",-1,1) | K13: =H13*I13 | L13: =G13*I13 | M13: =G13*H13 | N13: =J13*I13
A14: N-S-E-0 | B14: Nonlinear | C14: Static | D14: Economic | E14: None | F14: E25 | G14: =IF(B14="Nonlinear",1,-1) | H14: =IF(C14="State",1,-1) | I14: =IF(D14="Economic",1,-1) | J14: =IF(E14="None",-1,1) | K14: =H14*I14 | L14: =G14*I14 | M14: =G14*H14 | N14: =J14*I14
A15: N-S-E-U | B15: Nonlinear | C15: Static | D15: Economic | E15: Ensemble shrinkage | F15: E25 + E28 | G15: =IF(B15="Nonlinear",1,-1) | H15: =IF(C15="State",1,-1) | I15: =IF(D15="Economic",1,-1) | J15: =IF(E15="None",-1,1) | K15: =H15*I15 | L15: =G15*I15 | M15: =G15*H15 | N15: =J15*I15
... A19: N-C-E-U | B19: Nonlinear | C19: State | D19: Economic | E19: Ensemble shrinkage | F19: E27 + E28 | G19: =IF(B19="Nonlinear",1,-1) | H19: =IF(C19="State",1,-1) | I19: =IF(D19="Economic",1,-1) | J19: =IF(E19="None",-1,1) | K19: =H19*I19 | L19: =G19*I19 | M19: =G19*H19 | N19: =J19*I19
A21: Check: every contrast column sums to zero (orthogonal design) | G21: =SUM(G4:G19) | H21: =SUM(H4:H19) | I21: =SUM(I4:I19) | J21: =SUM(J4:J19) | K21: =SUM(K4:K19) | L21: =SUM(L4:L19) | M21: =SUM(M4:M19) | N21: =SUM(N4:N19)

Sheet Roadmap_Gantt
A1: Roadmap Gantt (formula-driven)
A2: Edit Start/End months; cells with 1 are shaded by conditional formatting
A3: Phase | B3: Start month | C3: End month | D3: 1 | E3: 2 | F3: 3 | G3: 4 | H3: 5 | I3: 6 | J3: 7 | K3: 8 | L3: 9 | M3: 10 | N3: 11 | O3: 12 | P3: 13 | Q3: 14 | R3: 15 | S3: 16
A4: 1. Literature + research design | B4: 1 | C4: 2 | D4: =IF(AND(D$3>=$B4,D$3<=$C4),1,"") | E4: =IF(AND(E$3>=$B4,E$3<=$C4),1,"") | F4: =IF(AND(F$3>=$B4,F$3<=$C4),1,"") | G4: =IF(AND(G$3>=$B4,G$3<=$C4),1,"") | H4: =IF(AND(H$3>=$B4,H$3<=$C4),1,"") | I4: =IF(AND(I$3>=$B4,I$3<=$C4),1,"") | J4: =IF(AND(J$3>=$B4,J$3<=$C4),1,"") | K4: =IF(AND(K$3>=$B4,K$3<=$C4),1,"") | ... S4: =IF(AND(S$3>=$B4,S$3<=$C4),1,"")
A5: 2. Data infrastructure | B5: 2 | C5: 4 | D5: =IF(AND(D$3>=$B5,D$3<=$C5),1,"") | E5: =IF(AND(E$3>=$B5,E$3<=$C5),1,"") | F5: =IF(AND(F$3>=$B5,F$3<=$C5),1,"") | G5: =IF(AND(G$3>=$B5,G$3<=$C5),1,"") | H5: =IF(AND(H$3>=$B5,H$3<=$C5),1,"") | I5: =IF(AND(I$3>=$B5,I$3<=$C5),1,"") | J5: =IF(AND(J$3>=$B5,J$3<=$C5),1,"") | K5: =IF(AND(K$3>=$B5,K$3<=$C5),1,"") | ... S5: =IF(AND(S$3>=$B5,S$3<=$C5),1,"")
A6: 3. Alpha signal library | B6: 3 | C6: 5 | D6: =IF(AND(D$3>=$B6,D$3<=$C6),1,"") | E6: =IF(AND(E$3>=$B6,E$3<=$C6),1,"") | F6: =IF(AND(F$3>=$B6,F$3<=$C6),1,"") | G6: =IF(AND(G$3>=$B6,G$3<=$C6),1,"") | H6: =IF(AND(H$3>=$B6,H$3<=$C6),1,"") | I6: =IF(AND(I$3>=$B6,I$3<=$C6),1,"") | J6: =IF(AND(J$3>=$B6,J$3<=$C6),1,"") | K6: =IF(AND(K$3>=$B6,K$3<=$C6),1,"") | ... S6: =IF(AND(S$3>=$B6,S$3<=$C6),1,"")
A7: 4. Baseline models | B7: 5 | C7: 6 | D7: =IF(AND(D$3>=$B7,D$3<=$C7),1,"") | E7: =IF(AND(E$3>=$B7,E$3<=$C7),1,"") | F7: =IF(AND(F$3>=$B7,F$3<=$C7),1,"") | G7: =IF(AND(G$3>=$B7,G$3<=$C7),1,"") | H7: =IF(AND(H$3>=$B7,H$3<=$C7),1,"") | I7: =IF(AND(I$3>=$B7,I$3<=$C7),1,"") | J7: =IF(AND(J$3>=$B7,J$3<=$C7),1,"") | K7: =IF(AND(K$3>=$B7,K$3<=$C7),1,"") | ... S7: =IF(AND(S$3>=$B7,S$3<=$C7),1,"")
A8: 5. ML signal combination | B8: 6 | C8: 9 | D8: =IF(AND(D$3>=$B8,D$3<=$C8),1,"") | E8: =IF(AND(E$3>=$B8,E$3<=$C8),1,"") | F8: =IF(AND(F$3>=$B8,F$3<=$C8),1,"") | G8: =IF(AND(G$3>=$B8,G$3<=$C8),1,"") | H8: =IF(AND(H$3>=$B8,H$3<=$C8),1,"") | I8: =IF(AND(I$3>=$B8,I$3<=$C8),1,"") | J8: =IF(AND(J$3>=$B8,J$3<=$C8),1,"") | K8: =IF(AND(K$3>=$B8,K$3<=$C8),1,"") | ... S8: =IF(AND(S$3>=$B8,S$3<=$C8),1,"")
A9: 6. Portfolio construction | B9: 8 | C9: 10 | D9: =IF(AND(D$3>=$B9,D$3<=$C9),1,"") | E9: =IF(AND(E$3>=$B9,E$3<=$C9),1,"") | F9: =IF(AND(F$3>=$B9,F$3<=$C9),1,"") | G9: =IF(AND(G$3>=$B9,G$3<=$C9),1,"") | H9: =IF(AND(H$3>=$B9,H$3<=$C9),1,"") | I9: =IF(AND(I$3>=$B9,I$3<=$C9),1,"") | J9: =IF(AND(J$3>=$B9,J$3<=$C9),1,"") | K9: =IF(AND(K$3>=$B9,K$3<=$C9),1,"") | ... S9: =IF(AND(S$3>=$B9,S$3<=$C9),1,"")
A10: 7. Robust backtesting | B10: 9 | C10: 11 | D10: =IF(AND(D$3>=$B10,D$3<=$C10),1,"") | E10: =IF(AND(E$3>=$B10,E$3<=$C10),1,"") | F10: =IF(AND(F$3>=$B10,F$3<=$C10),1,"") | G10: =IF(AND(G$3>=$B10,G$3<=$C10),1,"") | H10: =IF(AND(H$3>=$B10,H$3<=$C10),1,"") | I10: =IF(AND(I$3>=$B10,I$3<=$C10),1,"") | J10: =IF(AND(J$3>=$B10,J$3<=$C10),1,"") | K10: =IF(AND(K$3>=$B10,K$3<=$C10),1,"") | ... S10: =IF(AND(S$3>=$B10,S$3<=$C10),1,"")
A11: 8. Robustness + statistical testing | B11: 11 | C11: 13 | D11: =IF(AND(D$3>=$B11,D$3<=$C11),1,"") | E11: =IF(AND(E$3>=$B11,E$3<=$C11),1,"") | F11: =IF(AND(F$3>=$B11,F$3<=$C11),1,"") | G11: =IF(AND(G$3>=$B11,G$3<=$C11),1,"") | H11: =IF(AND(H$3>=$B11,H$3<=$C11),1,"") | I11: =IF(AND(I$3>=$B11,I$3<=$C11),1,"") | J11: =IF(AND(J$3>=$B11,J$3<=$C11),1,"") | K11: =IF(AND(K$3>=$B11,K$3<=$C11),1,"") | ... S11: =IF(AND(S$3>=$B11,S$3<=$C11),1,"")
A12: 9. Paper writing | B12: 12 | C12: 15 | D12: =IF(AND(D$3>=$B12,D$3<=$C12),1,"") | E12: =IF(AND(E$3>=$B12,E$3<=$C12),1,"") | F12: =IF(AND(F$3>=$B12,F$3<=$C12),1,"") | G12: =IF(AND(G$3>=$B12,G$3<=$C12),1,"") | H12: =IF(AND(H$3>=$B12,H$3<=$C12),1,"") | I12: =IF(AND(I$3>=$B12,I$3<=$C12),1,"") | J12: =IF(AND(J$3>=$B12,J$3<=$C12),1,"") | K12: =IF(AND(K$3>=$B12,K$3<=$C12),1,"") | ... S12: =IF(AND(S$3>=$B12,S$3<=$C12),1,"")
A13: 10. Journal submission | B13: 15 | C13: 16 | D13: =IF(AND(D$3>=$B13,D$3<=$C13),1,"") | E13: =IF(AND(E$3>=$B13,E$3<=$C13),1,"") | F13: =IF(AND(F$3>=$B13,F$3<=$C13),1,"") | G13: =IF(AND(G$3>=$B13,G$3<=$C13),1,"") | H13: =IF(AND(H$3>=$B13,H$3<=$C13),1,"") | I13: =IF(AND(I$3>=$B13,I$3<=$C13),1,"") | J13: =IF(AND(J$3>=$B13,J$3<=$C13),1,"") | K13: =IF(AND(K$3>=$B13,K$3<=$C13),1,"") | ... S13: =IF(AND(S$3>=$B13,S$3<=$C13),1,"")

Sheet Reviewer_Checklist
A1: Reviewer-proof checklist tracker
A2: Status dropdown; completion % recalculates | D2: Completion: | E2: =IFERROR(COUNTIF(C5:C69,"Done")/(COUNTA(B5:B69)-COUNTIF(C5:C69,"N/A")),0)
A4: Section | B4: Checklist item | C4: Status | D4: Evidence location | E4: Owner
A5: A. Contribution and positioning | B5: The research question is stated in one sentence as an economic question, not a model description. | C5: Not started
A6: A. Contribution and positioning | B6: The contribution statement names the closest papers (JKMP2026, SWZ2023, DMNU2020, DMU2024, GKX2020, ACM2023, CHK2024, LMNS2025) and says what is new relative to each. | C6: Not started
A7: A. Contribution and positioning | B7: The closest-prior-art tracker has been re-run within 2 weeks of submission (SSRN, NBER, arXiv, conference programmes, forward citations). | C7: Not started
A8: A. Contribution and positioning | B8: No "first to" claim appears unless the tracker supports it. | C8: Not started
A9: A. Contribution and positioning | B9: The hypotheses were pre-registered (dated document or OSF/AEA registry) before the lockbox was opened. | C9: Not started
A10: A. Contribution and positioning | B10: Null or negative results are reported, with power discussion. | C10: Not started
A11: B. Data and point-in-time integrity | B11: All data sources, pull dates and versions are documented. | C11: Not started
A12: B. Data and point-in-time integrity | B12: Accounting variables are lagged by availability (≥ 4 months annual; RDQ quarterly) and unit tests prove it. | C12: Not started
A13: B. Data and point-in-time integrity | B13: Universe formed at t from all live securities (no survivorship). | C13: Not started
A14: B. Data and point-in-time integrity | B14: CRSP delisting returns are applied; the convention for missing values is documented. | C14: Not started
A15: B. Data and point-in-time integrity | B15: Corporate actions are handled via CRSP adjustment factors and total returns. | C15: Not started
A16: B. Data and point-in-time integrity | B16: Microcaps are excluded from the main universe; results including them are in robustness. | C16: Not started
... A69: I. Reproducibility and presentation | B69: Limitations section covers cost-model uncertainty, US focus, and data licences. | C69: Not started
